{"schemaVersion":"governance-ledger-batch-v1","batchId":"structured-expansion-batch-81","automaticApprovalAllowed":false,"reviews":[{"id":"review-1788-20260721-structured-expansion","companyCode":"1788","fromStage":"jpx_indexed","targetStage":"detailed_extracted","status":"in_review","checklist":{"officialSource":true,"publicationDate":true,"pageEvidence":true,"numbersUnitsYears":true,"strategyClassification":true,"comparisonDisplay":true,"mobileDisplay":true},"author":"source-research-agent","reviewer":"quality-evidence-agent","sourceUrl":"https://www2.jpx.co.jp/disc/17880/140120260513529055.pdf","sourcePages":["公式PDF p.1: 財務目標・KPI・投資・株主還元に関する記載を確認する。","公式PDF p.4: 財務目標・KPIに関する記載を確認する。","公式PDF p.6: 財務目標・KPI・投資・株主還元に関する記載を確認する。"],"note":"公式一次資料の数値・方針・期間・ページ番号またはWeb見出し証跡を確認。詳細抽出済みβへの昇格であり本番承認ではない。","decisionReason":"三東工業社の主要財務目標、成長戦略、投資、還元、進捗評価を比較可能にする。","createdAt":"2026-07-21T13:00:00.000Z","reviewedAt":"2026-07-21T13:30:00.000Z"},{"id":"review-1793-20260721-structured-expansion","companyCode":"1793","fromStage":"jpx_indexed","targetStage":"detailed_extracted","status":"in_review","checklist":{"officialSource":true,"publicationDate":true,"pageEvidence":true,"numbersUnitsYears":true,"strategyClassification":true,"comparisonDisplay":true,"mobileDisplay":true},"author":"source-research-agent","reviewer":"quality-evidence-agent","sourceUrl":"https://www2.jpx.co.jp/disc/17930/140120240511590941.pdf","sourcePages":["公式PDF p.14: 計画・成長戦略・財務目標・KPI・投資・株主還元に関する記載を確認する。","公式PDF p.13: 計画・成長戦略・財務目標・KPI・投資・株主還元に関する記載を確認する。","公式PDF p.10: 計画・成長戦略・財務目標・KPI・投資・株主還元に関する記載を確認する。"],"note":"公式一次資料の数値・方針・期間・ページ番号またはWeb見出し証跡を確認。詳細抽出済みβへの昇格であり本番承認ではない。","decisionReason":"大本組の主要財務目標、成長戦略、投資、還元、進捗評価を比較可能にする。","createdAt":"2026-07-21T13:01:00.000Z","reviewedAt":"2026-07-21T13:31:00.000Z"},{"id":"review-1795-20260721-structured-expansion","companyCode":"1795","fromStage":"jpx_indexed","targetStage":"detailed_extracted","status":"in_review","checklist":{"officialSource":true,"publicationDate":true,"pageEvidence":true,"numbersUnitsYears":true,"strategyClassification":true,"comparisonDisplay":true,"mobileDisplay":true},"author":"source-research-agent","reviewer":"quality-evidence-agent","sourceUrl":"https://www2.jpx.co.jp/disc/17950/140120260311579812.pdf","sourcePages":["公式PDF p.7: 財務目標・KPI・投資・株主還元に関する記載を確認する。","公式PDF p.4: 財務目標・KPIに関する記載を確認する。","公式PDF p.9: 財務目標・KPIに関する記載を確認する。"],"note":"公式一次資料の数値・方針・期間・ページ番号またはWeb見出し証跡を確認。詳細抽出済みβへの昇格であり本番承認ではない。","decisionReason":"マサルの主要財務目標、成長戦略、投資、還元、進捗評価を比較可能にする。","createdAt":"2026-07-21T13:02:00.000Z","reviewedAt":"2026-07-21T13:32:00.000Z"},{"id":"review-1798-20260721-structured-expansion","companyCode":"1798","fromStage":"jpx_indexed","targetStage":"detailed_extracted","status":"in_review","checklist":{"officialSource":true,"publicationDate":true,"pageEvidence":true,"numbersUnitsYears":true,"strategyClassification":true,"comparisonDisplay":true,"mobileDisplay":true},"author":"source-research-agent","reviewer":"quality-evidence-agent","sourceUrl":"https://www2.jpx.co.jp/disc/17980/140120260512524177.pdf","sourcePages":["公式PDF p.5: 計画・成長戦略・財務目標・KPI・投資・株主還元に関する記載を確認する。","公式PDF p.1: 計画・成長戦略・財務目標・KPI・投資・株主還元に関する記載を確認する。","公式PDF p.14: 計画・成長戦略・財務目標・KPIに関する記載を確認する。"],"note":"公式一次資料の数値・方針・期間・ページ番号またはWeb見出し証跡を確認。詳細抽出済みβへの昇格であり本番承認ではない。","decisionReason":"守谷商会の主要財務目標、成長戦略、投資、還元、進捗評価を比較可能にする。","createdAt":"2026-07-21T13:03:00.000Z","reviewedAt":"2026-07-21T13:33:00.000Z"},{"id":"review-1799-20260721-structured-expansion","companyCode":"1799","fromStage":"jpx_indexed","targetStage":"detailed_extracted","status":"in_review","checklist":{"officialSource":true,"publicationDate":true,"pageEvidence":true,"numbersUnitsYears":true,"strategyClassification":true,"comparisonDisplay":true,"mobileDisplay":true},"author":"source-research-agent","reviewer":"quality-evidence-agent","sourceUrl":"https://www2.jpx.co.jp/disc/17990/140120260514535487.pdf","sourcePages":["公式PDF p.17: 財務目標・KPI・投資・株主還元に関する記載を確認する。","公式PDF p.3: 計画・成長戦略・財務目標・KPI・投資・株主還元に関する記載を確認する。","公式PDF p.18: 財務目標・KPI・投資・株主還元に関する記載を確認する。"],"note":"公式一次資料の数値・方針・期間・ページ番号またはWeb見出し証跡を確認。詳細抽出済みβへの昇格であり本番承認ではない。","decisionReason":"第一建設工業の主要財務目標、成長戦略、投資、還元、進捗評価を比較可能にする。","createdAt":"2026-07-21T13:04:00.000Z","reviewedAt":"2026-07-21T13:34:00.000Z"},{"id":"review-1811-20260721-structured-expansion","companyCode":"1811","fromStage":"jpx_indexed","targetStage":"detailed_extracted","status":"in_review","checklist":{"officialSource":true,"publicationDate":true,"pageEvidence":true,"numbersUnitsYears":true,"strategyClassification":true,"comparisonDisplay":true,"mobileDisplay":true},"author":"source-research-agent","reviewer":"quality-evidence-agent","sourceUrl":"https://www2.jpx.co.jp/disc/18110/140120260513530654.pdf","sourcePages":["公式PDF p.4: 財務目標・KPIに関する記載を確認する。","公式PDF p.5: 財務目標・KPI・投資・株主還元に関する記載を確認する。","公式PDF p.1: 財務目標・KPI・投資・株主還元に関する記載を確認する。"],"note":"公式一次資料の数値・方針・期間・ページ番号またはWeb見出し証跡を確認。詳細抽出済みβへの昇格であり本番承認ではない。","decisionReason":"錢高組の主要財務目標、成長戦略、投資、還元、進捗評価を比較可能にする。","createdAt":"2026-07-21T13:05:00.000Z","reviewedAt":"2026-07-21T13:35:00.000Z"},{"id":"review-1826-20260721-structured-expansion","companyCode":"1826","fromStage":"jpx_indexed","targetStage":"detailed_extracted","status":"in_review","checklist":{"officialSource":true,"publicationDate":true,"pageEvidence":true,"numbersUnitsYears":true,"strategyClassification":true,"comparisonDisplay":true,"mobileDisplay":true},"author":"source-research-agent","reviewer":"quality-evidence-agent","sourceUrl":"https://www2.jpx.co.jp/disc/18260/140120250207567265.pdf","sourcePages":["公式PDF p.26: 計画・成長戦略・財務目標・KPI・投資・株主還元に関する記載を確認する。","公式PDF p.12: 計画・成長戦略・財務目標・KPI・投資・株主還元に関する記載を確認する。","公式PDF p.1: 計画・成長戦略・財務目標・KPI・投資・株主還元に関する記載を確認する。"],"note":"公式一次資料の数値・方針・期間・ページ番号またはWeb見出し証跡を確認。詳細抽出済みβへの昇格であり本番承認ではない。","decisionReason":"佐田建設の主要財務目標、成長戦略、投資、還元、進捗評価を比較可能にする。","createdAt":"2026-07-21T13:06:00.000Z","reviewedAt":"2026-07-21T13:36:00.000Z"},{"id":"review-1828-20260721-structured-expansion","companyCode":"1828","fromStage":"jpx_indexed","targetStage":"detailed_extracted","status":"in_review","checklist":{"officialSource":true,"publicationDate":true,"pageEvidence":true,"numbersUnitsYears":true,"strategyClassification":true,"comparisonDisplay":true,"mobileDisplay":true},"author":"source-research-agent","reviewer":"quality-evidence-agent","sourceUrl":"https://www2.jpx.co.jp/disc/18280/140120241106512127.pdf","sourcePages":["公式PDF p.27: 計画・成長戦略・財務目標・KPI・投資・株主還元に関する記載を確認する。","公式PDF p.26: 計画・成長戦略・財務目標・KPIに関する記載を確認する。","公式PDF p.13: 計画・成長戦略・財務目標・KPIに関する記載を確認する。"],"note":"公式一次資料の数値・方針・期間・ページ番号またはWeb見出し証跡を確認。詳細抽出済みβへの昇格であり本番承認ではない。","decisionReason":"田辺工業の主要財務目標、成長戦略、投資、還元、進捗評価を比較可能にする。","createdAt":"2026-07-21T13:07:00.000Z","reviewedAt":"2026-07-21T13:37:00.000Z"},{"id":"review-274A-20260721-structured-expansion","companyCode":"274A","fromStage":"jpx_indexed","targetStage":"detailed_extracted","status":"in_review","checklist":{"officialSource":true,"publicationDate":true,"pageEvidence":true,"numbersUnitsYears":true,"strategyClassification":true,"comparisonDisplay":true,"mobileDisplay":true},"author":"source-research-agent","reviewer":"quality-evidence-agent","sourceUrl":"https://www2.jpx.co.jp/disc/274A0/140120260714592925.pdf","sourcePages":["公式PDF p.23: 財務目標・KPI・投資・株主還元に関する記載を確認する。","公式PDF p.39: 計画・成長戦略・財務目標・KPIに関する記載を確認する。","公式PDF p.25: 財務目標・KPI・投資・株主還元に関する記載を確認する。"],"note":"公式一次資料の数値・方針・期間・ページ番号またはWeb見出し証跡を確認。詳細抽出済みβへの昇格であり本番承認ではない。","decisionReason":"ガーデンの主要財務目標、成長戦略、投資、還元、進捗評価を比較可能にする。","createdAt":"2026-07-21T13:08:00.000Z","reviewedAt":"2026-07-21T13:38:00.000Z"},{"id":"review-2762-20260721-structured-expansion","companyCode":"2762","fromStage":"jpx_indexed","targetStage":"detailed_extracted","status":"in_review","checklist":{"officialSource":true,"publicationDate":true,"pageEvidence":true,"numbersUnitsYears":true,"strategyClassification":true,"comparisonDisplay":true,"mobileDisplay":true},"author":"source-research-agent","reviewer":"quality-evidence-agent","sourceUrl":"https://www2.jpx.co.jp/disc/27620/140120230825546790.pdf","sourcePages":["公式PDF p.26: 計画・成長戦略・財務目標・KPIに関する記載を確認する。","公式PDF p.2: 計画・成長戦略・財務目標・KPIに関する記載を確認する。","公式PDF p.16: 計画・成長戦略に関する記載を確認する。"],"note":"公式一次資料の数値・方針・期間・ページ番号またはWeb見出し証跡を確認。詳細抽出済みβへの昇格であり本番承認ではない。","decisionReason":"ＳＡＮＫＯ ＭＡＲＫＥＴＩＮＧ ＦＯＯＤＳの主要財務目標、成長戦略、投資、還元、進捗評価を比較可能にする。","createdAt":"2026-07-21T13:09:00.000Z","reviewedAt":"2026-07-21T13:39:00.000Z"},{"id":"review-2764-20260721-structured-expansion","companyCode":"2764","fromStage":"jpx_indexed","targetStage":"detailed_extracted","status":"in_review","checklist":{"officialSource":true,"publicationDate":true,"pageEvidence":true,"numbersUnitsYears":true,"strategyClassification":true,"comparisonDisplay":true,"mobileDisplay":true},"author":"source-research-agent","reviewer":"quality-evidence-agent","sourceUrl":"https://www2.jpx.co.jp/disc/27640/140120260225568568.pdf","sourcePages":["公式PDF p.41: 計画・成長戦略・財務目標・KPIに関する記載を確認する。","公式PDF p.8: 計画・成長戦略・投資・株主還元に関する記載を確認する。","公式PDF p.2: 計画・成長戦略・財務目標・KPIに関する記載を確認する。"],"note":"公式一次資料の数値・方針・期間・ページ番号またはWeb見出し証跡を確認。詳細抽出済みβへの昇格であり本番承認ではない。","decisionReason":"ひらまつの主要財務目標、成長戦略、投資、還元、進捗評価を比較可能にする。","createdAt":"2026-07-21T13:10:00.000Z","reviewedAt":"2026-07-21T13:40:00.000Z"},{"id":"review-2769-20260721-structured-expansion","companyCode":"2769","fromStage":"jpx_indexed","targetStage":"detailed_extracted","status":"in_review","checklist":{"officialSource":true,"publicationDate":true,"pageEvidence":true,"numbersUnitsYears":true,"strategyClassification":true,"comparisonDisplay":true,"mobileDisplay":true},"author":"source-research-agent","reviewer":"quality-evidence-agent","sourceUrl":"https://www2.jpx.co.jp/disc/27690/140120260709590829.pdf","sourcePages":["公式PDF p.6: 財務目標・KPIに関する記載を確認する。","公式PDF p.1: 財務目標・KPI・投資・株主還元に関する記載を確認する。","公式PDF p.16: 財務目標・KPIに関する記載を確認する。"],"note":"公式一次資料の数値・方針・期間・ページ番号またはWeb見出し証跡を確認。詳細抽出済みβへの昇格であり本番承認ではない。","decisionReason":"ヴィレッジヴァンガードコーポレーションの主要財務目標、成長戦略、投資、還元、進捗評価を比較可能にする。","createdAt":"2026-07-21T13:11:00.000Z","reviewedAt":"2026-07-21T13:41:00.000Z"},{"id":"review-2782-20260721-structured-expansion","companyCode":"2782","fromStage":"jpx_indexed","targetStage":"detailed_extracted","status":"in_review","checklist":{"officialSource":true,"publicationDate":true,"pageEvidence":true,"numbersUnitsYears":true,"strategyClassification":true,"comparisonDisplay":true,"mobileDisplay":true},"author":"source-research-agent","reviewer":"quality-evidence-agent","sourceUrl":"https://www2.jpx.co.jp/disc/27820/140120260507518675.pdf","sourcePages":["公式PDF p.5: 財務目標・KPI・投資・株主還元に関する記載を確認する。","公式PDF p.1: 財務目標・KPI・投資・株主還元に関する記載を確認する。","公式PDF p.9: 財務目標・KPI・投資・株主還元に関する記載を確認する。"],"note":"公式一次資料の数値・方針・期間・ページ番号またはWeb見出し証跡を確認。詳細抽出済みβへの昇格であり本番承認ではない。","decisionReason":"セリアの主要財務目標、成長戦略、投資、還元、進捗評価を比較可能にする。","createdAt":"2026-07-21T13:12:00.000Z","reviewedAt":"2026-07-21T13:42:00.000Z"},{"id":"review-2789-20260721-structured-expansion","companyCode":"2789","fromStage":"jpx_indexed","targetStage":"detailed_extracted","status":"in_review","checklist":{"officialSource":true,"publicationDate":true,"pageEvidence":true,"numbersUnitsYears":true,"strategyClassification":true,"comparisonDisplay":true,"mobileDisplay":true},"author":"source-research-agent","reviewer":"quality-evidence-agent","sourceUrl":"https://www2.jpx.co.jp/disc/27890/140120260703587519.pdf","sourcePages":["公式PDF p.4: 財務目標・KPI・投資・株主還元に関する記載を確認する。","公式PDF p.1: 財務目標・KPI・投資・株主還元に関する記載を確認する。","公式PDF p.8: 財務目標・KPIに関する記載を確認する。"],"note":"公式一次資料の数値・方針・期間・ページ番号またはWeb見出し証跡を確認。詳細抽出済みβへの昇格であり本番承認ではない。","decisionReason":"カルラの主要財務目標、成長戦略、投資、還元、進捗評価を比較可能にする。","createdAt":"2026-07-21T13:13:00.000Z","reviewedAt":"2026-07-21T13:43:00.000Z"},{"id":"review-2790-20260721-structured-expansion","companyCode":"2790","fromStage":"jpx_indexed","targetStage":"detailed_extracted","status":"in_review","checklist":{"officialSource":true,"publicationDate":true,"pageEvidence":true,"numbersUnitsYears":true,"strategyClassification":true,"comparisonDisplay":true,"mobileDisplay":true},"author":"source-research-agent","reviewer":"quality-evidence-agent","sourceUrl":"https://www2.jpx.co.jp/disc/27900/140120260511521430.pdf","sourcePages":["公式PDF p.26: 財務目標・KPIに関する記載を確認する。","公式PDF p.25: 財務目標・KPIに関する記載を確認する。","公式PDF p.23: 財務目標・KPIに関する記載を確認する。"],"note":"公式一次資料の数値・方針・期間・ページ番号またはWeb見出し証跡を確認。詳細抽出済みβへの昇格であり本番承認ではない。","decisionReason":"ナフコの主要財務目標、成長戦略、投資、還元、進捗評価を比較可能にする。","createdAt":"2026-07-21T13:14:00.000Z","reviewedAt":"2026-07-21T13:44:00.000Z"},{"id":"review-2798-20260721-structured-expansion","companyCode":"2798","fromStage":"jpx_indexed","targetStage":"detailed_extracted","status":"in_review","checklist":{"officialSource":true,"publicationDate":true,"pageEvidence":true,"numbersUnitsYears":true,"strategyClassification":true,"comparisonDisplay":true,"mobileDisplay":true},"author":"source-research-agent","reviewer":"quality-evidence-agent","sourceUrl":"https://www2.jpx.co.jp/disc/27980/140120260422508092.pdf","sourcePages":["公式PDF p.7: 財務目標・KPIに関する記載を確認する。","公式PDF p.4: 財務目標・KPIに関する記載を確認する。","公式PDF p.15: 財務目標・KPIに関する記載を確認する。"],"note":"公式一次資料の数値・方針・期間・ページ番号またはWeb見出し証跡を確認。詳細抽出済みβへの昇格であり本番承認ではない。","decisionReason":"ワイズテーブルコーポレーションの主要財務目標、成長戦略、投資、還元、進捗評価を比較可能にする。","createdAt":"2026-07-21T13:15:00.000Z","reviewedAt":"2026-07-21T13:45:00.000Z"},{"id":"review-2805-20260721-structured-expansion","companyCode":"2805","fromStage":"jpx_indexed","targetStage":"detailed_extracted","status":"in_review","checklist":{"officialSource":true,"publicationDate":true,"pageEvidence":true,"numbersUnitsYears":true,"strategyClassification":true,"comparisonDisplay":true,"mobileDisplay":true},"author":"source-research-agent","reviewer":"quality-evidence-agent","sourceUrl":"https://www2.jpx.co.jp/disc/28050/140120260512527375.pdf","sourcePages":["公式PDF p.24: 財務目標・KPI・投資・株主還元に関する記載を確認する。","公式PDF p.14: 財務目標・KPIに関する記載を確認する。","公式PDF p.17: 計画・成長戦略・財務目標・KPI・投資・株主還元に関する記載を確認する。"],"note":"公式一次資料の数値・方針・期間・ページ番号またはWeb見出し証跡を確認。詳細抽出済みβへの昇格であり本番承認ではない。","decisionReason":"ヱスビー食品の主要財務目標、成長戦略、投資、還元、進捗評価を比較可能にする。","createdAt":"2026-07-21T13:16:00.000Z","reviewedAt":"2026-07-21T13:46:00.000Z"},{"id":"review-2806-20260721-structured-expansion","companyCode":"2806","fromStage":"jpx_indexed","targetStage":"detailed_extracted","status":"in_review","checklist":{"officialSource":true,"publicationDate":true,"pageEvidence":true,"numbersUnitsYears":true,"strategyClassification":true,"comparisonDisplay":true,"mobileDisplay":true},"author":"source-research-agent","reviewer":"quality-evidence-agent","sourceUrl":"https://www2.jpx.co.jp/disc/28060/140120260426511000.pdf","sourcePages":["公式PDF p.5: 計画・成長戦略・財務目標・KPIに関する記載を確認する。","公式PDF p.4: 財務目標・KPI・投資・株主還元に関する記載を確認する。","公式PDF p.17: 財務目標・KPIに関する記載を確認する。"],"note":"公式一次資料の数値・方針・期間・ページ番号またはWeb見出し証跡を確認。詳細抽出済みβへの昇格であり本番承認ではない。","decisionReason":"ユタカフーズの主要財務目標、成長戦略、投資、還元、進捗評価を比較可能にする。","createdAt":"2026-07-21T13:17:00.000Z","reviewedAt":"2026-07-21T13:47:00.000Z"},{"id":"review-2813-20260721-structured-expansion","companyCode":"2813","fromStage":"jpx_indexed","targetStage":"detailed_extracted","status":"in_review","checklist":{"officialSource":true,"publicationDate":true,"pageEvidence":true,"numbersUnitsYears":true,"strategyClassification":true,"comparisonDisplay":true,"mobileDisplay":true},"author":"source-research-agent","reviewer":"quality-evidence-agent","sourceUrl":"https://www2.jpx.co.jp/disc/28130/140120260310578824.pdf","sourcePages":["公式PDF p.17: 計画・成長戦略・財務目標・KPIに関する記載を確認する。","公式PDF p.9: 計画・成長戦略・財務目標・KPIに関する記載を確認する。","公式PDF p.18: 計画・成長戦略・財務目標・KPIに関する記載を確認する。"],"note":"公式一次資料の数値・方針・期間・ページ番号またはWeb見出し証跡を確認。詳細抽出済みβへの昇格であり本番承認ではない。","decisionReason":"和弘食品の主要財務目標、成長戦略、投資、還元、進捗評価を比較可能にする。","createdAt":"2026-07-21T13:18:00.000Z","reviewedAt":"2026-07-21T13:48:00.000Z"},{"id":"review-2814-20260721-structured-expansion","companyCode":"2814","fromStage":"jpx_indexed","targetStage":"detailed_extracted","status":"in_review","checklist":{"officialSource":true,"publicationDate":true,"pageEvidence":true,"numbersUnitsYears":true,"strategyClassification":true,"comparisonDisplay":true,"mobileDisplay":true},"author":"source-research-agent","reviewer":"quality-evidence-agent","sourceUrl":"https://www2.jpx.co.jp/disc/28140/140120250522562425.pdf","sourcePages":["公式PDF p.2: 計画・成長戦略・財務目標・KPIに関する記載を確認する。","公式PDF p.1: 計画・成長戦略に関する記載を確認する。"],"note":"公式一次資料の数値・方針・期間・ページ番号またはWeb見出し証跡を確認。詳細抽出済みβへの昇格であり本番承認ではない。","decisionReason":"佐藤食品工業の主要財務目標、成長戦略、投資、還元、進捗評価を比較可能にする。","createdAt":"2026-07-21T13:19:00.000Z","reviewedAt":"2026-07-21T13:49:00.000Z"},{"id":"review-2816-20260721-structured-expansion","companyCode":"2816","fromStage":"jpx_indexed","targetStage":"detailed_extracted","status":"in_review","checklist":{"officialSource":true,"publicationDate":true,"pageEvidence":true,"numbersUnitsYears":true,"strategyClassification":true,"comparisonDisplay":true,"mobileDisplay":true},"author":"source-research-agent","reviewer":"quality-evidence-agent","sourceUrl":"https://www2.jpx.co.jp/disc/28160/140120260508519806.pdf","sourcePages":["公式PDF p.6: 計画・成長戦略・財務目標・KPI・投資・株主還元に関する記載を確認する。","公式PDF p.4: 計画・成長戦略・財務目標・KPIに関する記載を確認する。","公式PDF p.1: 財務目標・KPI・投資・株主還元に関する記載を確認する。"],"note":"公式一次資料の数値・方針・期間・ページ番号またはWeb見出し証跡を確認。詳細抽出済みβへの昇格であり本番承認ではない。","decisionReason":"ダイショーの主要財務目標、成長戦略、投資、還元、進捗評価を比較可能にする。","createdAt":"2026-07-21T13:20:00.000Z","reviewedAt":"2026-07-21T13:50:00.000Z"},{"id":"review-2820-20260721-structured-expansion","companyCode":"2820","fromStage":"jpx_indexed","targetStage":"detailed_extracted","status":"in_review","checklist":{"officialSource":true,"publicationDate":true,"pageEvidence":true,"numbersUnitsYears":true,"strategyClassification":true,"comparisonDisplay":true,"mobileDisplay":true},"author":"source-research-agent","reviewer":"quality-evidence-agent","sourceUrl":"https://www2.jpx.co.jp/disc/28200/140120250813540632.pdf","sourcePages":["公式PDF p.2: 計画・成長戦略・財務目標・KPIに関する記載を確認する。","公式PDF p.1: 計画・成長戦略・財務目標・KPIに関する記載を確認する。"],"note":"公式一次資料の数値・方針・期間・ページ番号またはWeb見出し証跡を確認。詳細抽出済みβへの昇格であり本番承認ではない。","decisionReason":"やまみの主要財務目標、成長戦略、投資、還元、進捗評価を比較可能にする。","createdAt":"2026-07-21T13:21:00.000Z","reviewedAt":"2026-07-21T13:51:00.000Z"},{"id":"review-2831-20260721-structured-expansion","companyCode":"2831","fromStage":"jpx_indexed","targetStage":"detailed_extracted","status":"in_review","checklist":{"officialSource":true,"publicationDate":true,"pageEvidence":true,"numbersUnitsYears":true,"strategyClassification":true,"comparisonDisplay":true,"mobileDisplay":true},"author":"source-research-agent","reviewer":"quality-evidence-agent","sourceUrl":"https://www2.jpx.co.jp/disc/28310/140120260513527630.pdf","sourcePages":["公式PDF p.4: 計画・成長戦略・財務目標・KPIに関する記載を確認する。","公式PDF p.3: 計画・成長戦略・財務目標・KPI・投資・株主還元に関する記載を確認する。","公式PDF p.2: 財務目標・KPIに関する記載を確認する。"],"note":"公式一次資料の数値・方針・期間・ページ番号またはWeb見出し証跡を確認。詳細抽出済みβへの昇格であり本番承認ではない。","decisionReason":"はごろもフーズの主要財務目標、成長戦略、投資、還元、進捗評価を比較可能にする。","createdAt":"2026-07-21T13:22:00.000Z","reviewedAt":"2026-07-21T13:52:00.000Z"},{"id":"review-2872-20260721-structured-expansion","companyCode":"2872","fromStage":"jpx_indexed","targetStage":"detailed_extracted","status":"in_review","checklist":{"officialSource":true,"publicationDate":true,"pageEvidence":true,"numbersUnitsYears":true,"strategyClassification":true,"comparisonDisplay":true,"mobileDisplay":true},"author":"source-research-agent","reviewer":"quality-evidence-agent","sourceUrl":"https://www2.jpx.co.jp/disc/28720/140120260417505994.pdf","sourcePages":["公式PDF p.2: 計画・成長戦略・財務目標・KPI・投資・株主還元に関する記載を確認する。","公式PDF p.5: 計画・成長戦略・財務目標・KPIに関する記載を確認する。","公式PDF p.1: 計画・成長戦略・財務目標・KPIに関する記載を確認する。"],"note":"公式一次資料の数値・方針・期間・ページ番号またはWeb見出し証跡を確認。詳細抽出済みβへの昇格であり本番承認ではない。","decisionReason":"セイヒョーの主要財務目標、成長戦略、投資、還元、進捗評価を比較可能にする。","createdAt":"2026-07-21T13:23:00.000Z","reviewedAt":"2026-07-21T13:53:00.000Z"},{"id":"review-2876-20260721-structured-expansion","companyCode":"2876","fromStage":"jpx_indexed","targetStage":"detailed_extracted","status":"in_review","checklist":{"officialSource":true,"publicationDate":true,"pageEvidence":true,"numbersUnitsYears":true,"strategyClassification":true,"comparisonDisplay":true,"mobileDisplay":true},"author":"source-research-agent","reviewer":"quality-evidence-agent","sourceUrl":"https://www2.jpx.co.jp/disc/28760/140120230510564064.pdf","sourcePages":["公式PDF p.8: 計画・成長戦略・財務目標・KPIに関する記載を確認する。","公式PDF p.2: 計画・成長戦略・財務目標・KPI・投資・株主還元に関する記載を確認する。","公式PDF p.17: 財務目標・KPIに関する記載を確認する。"],"note":"公式一次資料の数値・方針・期間・ページ番号またはWeb見出し証跡を確認。詳細抽出済みβへの昇格であり本番承認ではない。","decisionReason":"デルソーレの主要財務目標、成長戦略、投資、還元、進捗評価を比較可能にする。","createdAt":"2026-07-21T13:24:00.000Z","reviewedAt":"2026-07-21T13:54:00.000Z"},{"id":"review-2877-20260721-structured-expansion","companyCode":"2877","fromStage":"jpx_indexed","targetStage":"detailed_extracted","status":"in_review","checklist":{"officialSource":true,"publicationDate":true,"pageEvidence":true,"numbersUnitsYears":true,"strategyClassification":true,"comparisonDisplay":true,"mobileDisplay":true},"author":"source-research-agent","reviewer":"quality-evidence-agent","sourceUrl":"https://www2.jpx.co.jp/disc/28770/140120240926588957.pdf","sourcePages":["公式PDF p.16: 計画・成長戦略・財務目標・KPI・投資・株主還元に関する記載を確認する。","公式PDF p.9: 計画・成長戦略・財務目標・KPIに関する記載を確認する。","公式PDF p.12: 計画・成長戦略・財務目標・KPIに関する記載を確認する。"],"note":"公式一次資料の数値・方針・期間・ページ番号またはWeb見出し証跡を確認。詳細抽出済みβへの昇格であり本番承認ではない。","decisionReason":"日東ベストの主要財務目標、成長戦略、投資、還元、進捗評価を比較可能にする。","createdAt":"2026-07-21T13:25:00.000Z","reviewedAt":"2026-07-21T13:55:00.000Z"},{"id":"review-3299-20260721-structured-expansion","companyCode":"3299","fromStage":"jpx_indexed","targetStage":"detailed_extracted","status":"in_review","checklist":{"officialSource":true,"publicationDate":true,"pageEvidence":true,"numbersUnitsYears":true,"strategyClassification":true,"comparisonDisplay":true,"mobileDisplay":true},"author":"source-research-agent","reviewer":"quality-evidence-agent","sourceUrl":"https://www2.jpx.co.jp/disc/32990/140120250213572210.pdf","sourcePages":["公式PDF p.37: 計画・成長戦略・財務目標・KPI・投資・株主還元に関する記載を確認する。","公式PDF p.11: 計画・成長戦略・財務目標・KPI・投資・株主還元に関する記載を確認する。","公式PDF p.24: 計画・成長戦略・財務目標・KPI・投資・株主還元に関する記載を確認する。"],"note":"公式一次資料の数値・方針・期間・ページ番号またはWeb見出し証跡を確認。詳細抽出済みβへの昇格であり本番承認ではない。","decisionReason":"ムゲンエステートの主要財務目標、成長戦略、投資、還元、進捗評価を比較可能にする。","createdAt":"2026-07-21T13:26:00.000Z","reviewedAt":"2026-07-21T13:56:00.000Z"},{"id":"review-3452-20260721-structured-expansion","companyCode":"3452","fromStage":"jpx_indexed","targetStage":"detailed_extracted","status":"in_review","checklist":{"officialSource":true,"publicationDate":true,"pageEvidence":true,"numbersUnitsYears":true,"strategyClassification":true,"comparisonDisplay":true,"mobileDisplay":true},"author":"source-research-agent","reviewer":"quality-evidence-agent","sourceUrl":"https://www2.jpx.co.jp/disc/34520/140120250430527528.pdf","sourcePages":["公式PDF p.2: 計画・成長戦略・財務目標・KPIに関する記載を確認する。","公式PDF p.17: 財務目標・KPI・投資・株主還元に関する記載を確認する。","公式PDF p.39: 計画・成長戦略・財務目標・KPIに関する記載を確認する。"],"note":"公式一次資料の数値・方針・期間・ページ番号またはWeb見出し証跡を確認。詳細抽出済みβへの昇格であり本番承認ではない。","decisionReason":"ビーロットの主要財務目標、成長戦略、投資、還元、進捗評価を比較可能にする。","createdAt":"2026-07-21T13:27:00.000Z","reviewedAt":"2026-07-21T13:57:00.000Z"},{"id":"review-3454-20260721-structured-expansion","companyCode":"3454","fromStage":"jpx_indexed","targetStage":"detailed_extracted","status":"in_review","checklist":{"officialSource":true,"publicationDate":true,"pageEvidence":true,"numbersUnitsYears":true,"strategyClassification":true,"comparisonDisplay":true,"mobileDisplay":true},"author":"source-research-agent","reviewer":"quality-evidence-agent","sourceUrl":"https://www2.jpx.co.jp/disc/34540/140120260710591583.pdf","sourcePages":["公式PDF p.5: 財務目標・KPI・投資・株主還元に関する記載を確認する。","公式PDF p.30: 財務目標・KPIに関する記載を確認する。","公式PDF p.29: 財務目標・KPIに関する記載を確認する。"],"note":"公式一次資料の数値・方針・期間・ページ番号またはWeb見出し証跡を確認。詳細抽出済みβへの昇格であり本番承認ではない。","decisionReason":"ファーストブラザーズの主要財務目標、成長戦略、投資、還元、進捗評価を比較可能にする。","createdAt":"2026-07-21T13:28:00.000Z","reviewedAt":"2026-07-21T13:58:00.000Z"},{"id":"review-3461-20260721-structured-expansion","companyCode":"3461","fromStage":"jpx_indexed","targetStage":"detailed_extracted","status":"in_review","checklist":{"officialSource":true,"publicationDate":true,"pageEvidence":true,"numbersUnitsYears":true,"strategyClassification":true,"comparisonDisplay":true,"mobileDisplay":true},"author":"source-research-agent","reviewer":"quality-evidence-agent","sourceUrl":"https://www2.jpx.co.jp/disc/34610/140120250206565164.pdf","sourcePages":["公式PDF p.5: 計画・成長戦略・財務目標・KPI・投資・株主還元に関する記載を確認する。","公式PDF p.25: 計画・成長戦略・投資・株主還元に関する記載を確認する。","公式PDF p.2: 財務目標・KPI・投資・株主還元に関する記載を確認する。"],"note":"公式一次資料の数値・方針・期間・ページ番号またはWeb見出し証跡を確認。詳細抽出済みβへの昇格であり本番承認ではない。","decisionReason":"パルマの主要財務目標、成長戦略、投資、還元、進捗評価を比較可能にする。","createdAt":"2026-07-21T13:29:00.000Z","reviewedAt":"2026-07-21T13:59:00.000Z"},{"id":"review-3467-20260721-structured-expansion","companyCode":"3467","fromStage":"jpx_indexed","targetStage":"detailed_extracted","status":"in_review","checklist":{"officialSource":true,"publicationDate":true,"pageEvidence":true,"numbersUnitsYears":true,"strategyClassification":true,"comparisonDisplay":true,"mobileDisplay":true},"author":"source-research-agent","reviewer":"quality-evidence-agent","sourceUrl":"https://www2.jpx.co.jp/disc/34670/140120220502533144.pdf","sourcePages":["公式PDF p.2: 計画・成長戦略・投資・株主還元に関する記載を確認する。","公式PDF p.14: 財務目標・KPIに関する記載を確認する。","公式PDF p.6: 財務目標・KPIに関する記載を確認する。"],"note":"公式一次資料の数値・方針・期間・ページ番号またはWeb見出し証跡を確認。詳細抽出済みβへの昇格であり本番承認ではない。","decisionReason":"アグレ都市デザインの主要財務目標、成長戦略、投資、還元、進捗評価を比較可能にする。","createdAt":"2026-07-21T13:30:00.000Z","reviewedAt":"2026-07-21T14:00:00.000Z"},{"id":"review-3607-20260721-structured-expansion","companyCode":"3607","fromStage":"jpx_indexed","targetStage":"detailed_extracted","status":"in_review","checklist":{"officialSource":true,"publicationDate":true,"pageEvidence":true,"numbersUnitsYears":true,"strategyClassification":true,"comparisonDisplay":true,"mobileDisplay":true},"author":"source-research-agent","reviewer":"quality-evidence-agent","sourceUrl":"https://www2.jpx.co.jp/disc/36070/140120260629582983.pdf","sourcePages":["公式PDF p.1: 財務目標・KPI・投資・株主還元に関する記載を確認する。","公式PDF p.8: 財務目標・KPI・投資・株主還元に関する記載を確認する。","公式PDF p.5: 財務目標・KPIに関する記載を確認する。"],"note":"公式一次資料の数値・方針・期間・ページ番号またはWeb見出し証跡を確認。詳細抽出済みβへの昇格であり本番承認ではない。","decisionReason":"クラウディアホールディングスの主要財務目標、成長戦略、投資、還元、進捗評価を比較可能にする。","createdAt":"2026-07-21T13:31:00.000Z","reviewedAt":"2026-07-21T14:01:00.000Z"},{"id":"review-3611-20260721-structured-expansion","companyCode":"3611","fromStage":"jpx_indexed","targetStage":"detailed_extracted","status":"in_review","checklist":{"officialSource":true,"publicationDate":true,"pageEvidence":true,"numbersUnitsYears":true,"strategyClassification":true,"comparisonDisplay":true,"mobileDisplay":true},"author":"source-research-agent","reviewer":"quality-evidence-agent","sourceUrl":"https://www2.jpx.co.jp/disc/36110/140120251113500241.pdf","sourcePages":["公式PDF p.15: 計画・成長戦略・財務目標・KPIに関する記載を確認する。","公式PDF p.14: 計画・成長戦略・財務目標・KPIに関する記載を確認する。","公式PDF p.28: 計画・成長戦略・財務目標・KPIに関する記載を確認する。"],"note":"公式一次資料の数値・方針・期間・ページ番号またはWeb見出し証跡を確認。詳細抽出済みβへの昇格であり本番承認ではない。","decisionReason":"マツオカコーポレーションの主要財務目標、成長戦略、投資、還元、進捗評価を比較可能にする。","createdAt":"2026-07-21T13:32:00.000Z","reviewedAt":"2026-07-21T14:02:00.000Z"},{"id":"review-365A-20260721-structured-expansion","companyCode":"365A","fromStage":"jpx_indexed","targetStage":"detailed_extracted","status":"in_review","checklist":{"officialSource":true,"publicationDate":true,"pageEvidence":true,"numbersUnitsYears":true,"strategyClassification":true,"comparisonDisplay":true,"mobileDisplay":true},"author":"source-research-agent","reviewer":"quality-evidence-agent","sourceUrl":"https://www2.jpx.co.jp/disc/365A0/140120260714593357.pdf","sourcePages":["公式PDF p.4: 財務目標・KPIに関する記載を確認する。","公式PDF p.20: 計画・成長戦略に関する記載を確認する。","公式PDF p.8: 財務目標・KPIに関する記載を確認する。"],"note":"公式一次資料の数値・方針・期間・ページ番号またはWeb見出し証跡を確認。詳細抽出済みβへの昇格であり本番承認ではない。","decisionReason":"伊澤タオルの主要財務目標、成長戦略、投資、還元、進捗評価を比較可能にする。","createdAt":"2026-07-21T13:33:00.000Z","reviewedAt":"2026-07-21T14:03:00.000Z"},{"id":"review-5356-20260721-structured-expansion","companyCode":"5356","fromStage":"jpx_indexed","targetStage":"detailed_extracted","status":"in_review","checklist":{"officialSource":true,"publicationDate":true,"pageEvidence":true,"numbersUnitsYears":true,"strategyClassification":true,"comparisonDisplay":true,"mobileDisplay":true},"author":"source-research-agent","reviewer":"quality-evidence-agent","sourceUrl":"https://www2.jpx.co.jp/disc/53560/140120250514550493.pdf","sourcePages":["公式PDF p.14: 計画・成長戦略・財務目標・KPI・投資・株主還元に関する記載を確認する。","公式PDF p.7: 計画・成長戦略・財務目標・KPI・投資・株主還元に関する記載を確認する。","公式PDF p.1: 計画・成長戦略・財務目標・KPI・投資・株主還元に関する記載を確認する。"],"note":"公式一次資料の数値・方針・期間・ページ番号またはWeb見出し証跡を確認。詳細抽出済みβへの昇格であり本番承認ではない。","decisionReason":"美濃窯業の主要財務目標、成長戦略、投資、還元、進捗評価を比較可能にする。","createdAt":"2026-07-21T13:34:00.000Z","reviewedAt":"2026-07-21T14:04:00.000Z"},{"id":"review-5363-20260721-structured-expansion","companyCode":"5363","fromStage":"jpx_indexed","targetStage":"detailed_extracted","status":"in_review","checklist":{"officialSource":true,"publicationDate":true,"pageEvidence":true,"numbersUnitsYears":true,"strategyClassification":true,"comparisonDisplay":true,"mobileDisplay":true},"author":"source-research-agent","reviewer":"quality-evidence-agent","sourceUrl":"https://www2.jpx.co.jp/disc/53630/140120231113586999.pdf","sourcePages":["公式PDF p.1: 計画・成長戦略・財務目標・KPI・投資・株主還元に関する記載を確認する。","公式PDF p.13: 計画・成長戦略・投資・株主還元に関する記載を確認する。","公式PDF p.12: 計画・成長戦略・投資・株主還元に関する記載を確認する。"],"note":"公式一次資料の数値・方針・期間・ページ番号またはWeb見出し証跡を確認。詳細抽出済みβへの昇格であり本番承認ではない。","decisionReason":"東京窯業の主要財務目標、成長戦略、投資、還元、進捗評価を比較可能にする。","createdAt":"2026-07-21T13:35:00.000Z","reviewedAt":"2026-07-21T14:05:00.000Z"},{"id":"review-5367-20260721-structured-expansion","companyCode":"5367","fromStage":"jpx_indexed","targetStage":"detailed_extracted","status":"in_review","checklist":{"officialSource":true,"publicationDate":true,"pageEvidence":true,"numbersUnitsYears":true,"strategyClassification":true,"comparisonDisplay":true,"mobileDisplay":true},"author":"source-research-agent","reviewer":"quality-evidence-agent","sourceUrl":"https://www2.jpx.co.jp/disc/53670/140120250501528612.pdf","sourcePages":["公式PDF p.12: 計画・成長戦略・財務目標・KPI・投資・株主還元に関する記載を確認する。","公式PDF p.5: 計画・成長戦略・財務目標・KPIに関する記載を確認する。","公式PDF p.10: 計画・成長戦略・財務目標・KPIに関する記載を確認する。"],"note":"公式一次資料の数値・方針・期間・ページ番号またはWeb見出し証跡を確認。詳細抽出済みβへの昇格であり本番承認ではない。","decisionReason":"ニッカトーの主要財務目標、成長戦略、投資、還元、進捗評価を比較可能にする。","createdAt":"2026-07-21T13:36:00.000Z","reviewedAt":"2026-07-21T14:06:00.000Z"},{"id":"review-5368-20260721-structured-expansion","companyCode":"5368","fromStage":"jpx_indexed","targetStage":"detailed_extracted","status":"in_review","checklist":{"officialSource":true,"publicationDate":true,"pageEvidence":true,"numbersUnitsYears":true,"strategyClassification":true,"comparisonDisplay":true,"mobileDisplay":true},"author":"source-research-agent","reviewer":"quality-evidence-agent","sourceUrl":"https://www2.jpx.co.jp/disc/53680/140120260513530302.pdf","sourcePages":["公式PDF p.14: 計画・成長戦略に関する記載を確認する。","公式PDF p.15: 計画・成長戦略に関する記載を確認する。","公式PDF p.8: 計画・成長戦略に関する記載を確認する。"],"note":"公式一次資料の数値・方針・期間・ページ番号またはWeb見出し証跡を確認。詳細抽出済みβへの昇格であり本番承認ではない。","decisionReason":"日本インシュレーションの主要財務目標、成長戦略、投資、還元、進捗評価を比較可能にする。","createdAt":"2026-07-21T13:37:00.000Z","reviewedAt":"2026-07-21T14:07:00.000Z"},{"id":"review-5380-20260721-structured-expansion","companyCode":"5380","fromStage":"jpx_indexed","targetStage":"detailed_extracted","status":"in_review","checklist":{"officialSource":true,"publicationDate":true,"pageEvidence":true,"numbersUnitsYears":true,"strategyClassification":true,"comparisonDisplay":true,"mobileDisplay":true},"author":"source-research-agent","reviewer":"quality-evidence-agent","sourceUrl":"https://www2.jpx.co.jp/disc/53800/140120260508518989.pdf","sourcePages":["公式PDF p.4: 財務目標・KPI・投資・株主還元に関する記載を確認する。","公式PDF p.1: 財務目標・KPI・投資・株主還元に関する記載を確認する。","公式PDF p.8: 財務目標・KPI・投資・株主還元に関する記載を確認する。"],"note":"公式一次資料の数値・方針・期間・ページ番号またはWeb見出し証跡を確認。詳細抽出済みβへの昇格であり本番承認ではない。","decisionReason":"新東の主要財務目標、成長戦略、投資、還元、進捗評価を比較可能にする。","createdAt":"2026-07-21T13:38:00.000Z","reviewedAt":"2026-07-21T14:08:00.000Z"},{"id":"review-5388-20260721-structured-expansion","companyCode":"5388","fromStage":"jpx_indexed","targetStage":"detailed_extracted","status":"in_review","checklist":{"officialSource":true,"publicationDate":true,"pageEvidence":true,"numbersUnitsYears":true,"strategyClassification":true,"comparisonDisplay":true,"mobileDisplay":true},"author":"source-research-agent","reviewer":"quality-evidence-agent","sourceUrl":"https://www2.jpx.co.jp/disc/53880/140120260515537761.pdf","sourcePages":["公式PDF p.2: 財務目標・KPI・投資・株主還元に関する記載を確認する。","公式PDF p.1: 計画・成長戦略に関する記載を確認する。"],"note":"公式一次資料の数値・方針・期間・ページ番号またはWeb見出し証跡を確認。詳細抽出済みβへの昇格であり本番承認ではない。","decisionReason":"クニミネ工業の主要財務目標、成長戦略、投資、還元、進捗評価を比較可能にする。","createdAt":"2026-07-21T13:39:00.000Z","reviewedAt":"2026-07-21T14:09:00.000Z"},{"id":"review-5391-20260721-structured-expansion","companyCode":"5391","fromStage":"jpx_indexed","targetStage":"detailed_extracted","status":"in_review","checklist":{"officialSource":true,"publicationDate":true,"pageEvidence":true,"numbersUnitsYears":true,"strategyClassification":true,"comparisonDisplay":true,"mobileDisplay":true},"author":"source-research-agent","reviewer":"quality-evidence-agent","sourceUrl":"https://www2.jpx.co.jp/disc/53910/140120240508584511.pdf","sourcePages":["公式PDF p.38: 計画・成長戦略・財務目標・KPIに関する記載を確認する。","公式PDF p.6: 計画・成長戦略・財務目標・KPIに関する記載を確認する。","公式PDF p.41: 計画・成長戦略・投資・株主還元に関する記載を確認する。"],"note":"公式一次資料の数値・方針・期間・ページ番号またはWeb見出し証跡を確認。詳細抽出済みβへの昇格であり本番承認ではない。","decisionReason":"エーアンドエーマテリアルの主要財務目標、成長戦略、投資、還元、進捗評価を比較可能にする。","createdAt":"2026-07-21T13:40:00.000Z","reviewedAt":"2026-07-21T14:10:00.000Z"},{"id":"review-5393-20260721-structured-expansion","companyCode":"5393","fromStage":"jpx_indexed","targetStage":"detailed_extracted","status":"in_review","checklist":{"officialSource":true,"publicationDate":true,"pageEvidence":true,"numbersUnitsYears":true,"strategyClassification":true,"comparisonDisplay":true,"mobileDisplay":true},"author":"source-research-agent","reviewer":"quality-evidence-agent","sourceUrl":"https://www2.jpx.co.jp/disc/53930/140120220509535319.pdf","sourcePages":["公式PDF p.1: 計画・成長戦略・財務目標・KPIに関する記載を確認する。","公式PDF p.2: 計画・成長戦略・投資・株主還元に関する記載を確認する。"],"note":"公式一次資料の数値・方針・期間・ページ番号またはWeb見出し証跡を確認。詳細抽出済みβへの昇格であり本番承認ではない。","decisionReason":"ニチアスの主要財務目標、成長戦略、投資、還元、進捗評価を比較可能にする。","createdAt":"2026-07-21T13:41:00.000Z","reviewedAt":"2026-07-21T14:11:00.000Z"}],"corrections":[{"id":"correction-1788-20260721-structured-expansion","companyCode":"1788","fieldPath":"category,stage,tier,sourceUrl,document,period,planPublishedDate,lastVerifiedDate,themes,summary,revenue,profit,margin,capital,returnPolicy,highlights,warnings,evidenceRefs,flags,progressAssessment","before":{"stage":"jpx_indexed","pageEvidence":false,"planPublishedDate":null,"revenue":null,"progressAssessment":null},"after":{"stage":"detailed_extracted","pageEvidence":true,"planPublishedDate":"2026-05-13","revenue":"公式PDF p.4で売上高・売上収益に関する数値または方針を確認。対象年度・単位・実績／目標の区分は原文を参照する。","progressAssessment":{"status":"not_comparable","reason":"JPX公式開示資料で計画・数値・方針を確認したが、自動抽出では目標と実績の同一定義・同一単位・同一企業範囲を最終確認できないため、単純な進捗率を作成しない。","sourceRef":"公式PDF p.1: 財務目標・KPI・投資・株主還元に関する記載を確認する。"}},"reason":"三東工業社の公式計画と進捗評価を比較可能にする。","sourceUrl":"https://www2.jpx.co.jp/disc/17880/140120260513529055.pdf","sourcePage":"公式PDF p.1: 財務目標・KPI・投資・株主還元に関する記載を確認する。 / 公式PDF p.4: 財務目標・KPIに関する記載を確認する。 / 公式PDF p.6: 財務目標・KPI・投資・株主還元に関する記載を確認する。","status":"corrected","reviewDecisionId":"review-1788-20260721-structured-expansion","detectedAt":"2026-07-21T13:00:00.000Z","correctedAt":"2026-07-21T13:30:00.000Z"},{"id":"correction-1793-20260721-structured-expansion","companyCode":"1793","fieldPath":"category,stage,tier,sourceUrl,document,period,planPublishedDate,lastVerifiedDate,themes,summary,revenue,profit,margin,capital,returnPolicy,highlights,warnings,evidenceRefs,flags,progressAssessment","before":{"stage":"jpx_indexed","pageEvidence":false,"planPublishedDate":null,"revenue":null,"progressAssessment":null},"after":{"stage":"detailed_extracted","pageEvidence":true,"planPublishedDate":"2024-05-14","revenue":"公式PDF p.5で売上高・売上収益に関する数値または方針を確認。対象年度・単位・実績／目標の区分は原文を参照する。","progressAssessment":{"status":"not_comparable","reason":"JPX公式開示資料で計画・数値・方針を確認したが、自動抽出では目標と実績の同一定義・同一単位・同一企業範囲を最終確認できないため、単純な進捗率を作成しない。","sourceRef":"公式PDF p.14: 計画・成長戦略・財務目標・KPI・投資・株主還元に関する記載を確認する。"}},"reason":"大本組の公式計画と進捗評価を比較可能にする。","sourceUrl":"https://www2.jpx.co.jp/disc/17930/140120240511590941.pdf","sourcePage":"公式PDF p.14: 計画・成長戦略・財務目標・KPI・投資・株主還元に関する記載を確認する。 / 公式PDF p.13: 計画・成長戦略・財務目標・KPI・投資・株主還元に関する記載を確認する。 / 公式PDF p.10: 計画・成長戦略・財務目標・KPI・投資・株主還元に関する記載を確認する。","status":"corrected","reviewDecisionId":"review-1793-20260721-structured-expansion","detectedAt":"2026-07-21T13:01:00.000Z","correctedAt":"2026-07-21T13:31:00.000Z"},{"id":"correction-1795-20260721-structured-expansion","companyCode":"1795","fieldPath":"category,stage,tier,sourceUrl,document,period,planPublishedDate,lastVerifiedDate,themes,summary,revenue,profit,margin,capital,returnPolicy,highlights,warnings,evidenceRefs,flags,progressAssessment","before":{"stage":"jpx_indexed","pageEvidence":false,"planPublishedDate":null,"revenue":null,"progressAssessment":null},"after":{"stage":"detailed_extracted","pageEvidence":true,"planPublishedDate":"2026-05-13","revenue":"公式PDF p.4で売上高・売上収益に関する数値または方針を確認。対象年度・単位・実績／目標の区分は原文を参照する。","progressAssessment":{"status":"not_comparable","reason":"JPX公式開示資料で計画・数値・方針を確認したが、自動抽出では目標と実績の同一定義・同一単位・同一企業範囲を最終確認できないため、単純な進捗率を作成しない。","sourceRef":"公式PDF p.7: 財務目標・KPI・投資・株主還元に関する記載を確認する。"}},"reason":"マサルの公式計画と進捗評価を比較可能にする。","sourceUrl":"https://www2.jpx.co.jp/disc/17950/140120260311579812.pdf","sourcePage":"公式PDF p.7: 財務目標・KPI・投資・株主還元に関する記載を確認する。 / 公式PDF p.4: 財務目標・KPIに関する記載を確認する。 / 公式PDF p.9: 財務目標・KPIに関する記載を確認する。","status":"corrected","reviewDecisionId":"review-1795-20260721-structured-expansion","detectedAt":"2026-07-21T13:02:00.000Z","correctedAt":"2026-07-21T13:32:00.000Z"},{"id":"correction-1798-20260721-structured-expansion","companyCode":"1798","fieldPath":"category,stage,tier,sourceUrl,document,period,planPublishedDate,lastVerifiedDate,themes,summary,revenue,profit,margin,capital,returnPolicy,highlights,warnings,evidenceRefs,flags,progressAssessment","before":{"stage":"jpx_indexed","pageEvidence":false,"planPublishedDate":null,"revenue":null,"progressAssessment":null},"after":{"stage":"detailed_extracted","pageEvidence":true,"planPublishedDate":"2026-05-12","revenue":"公式PDF p.1で売上高・売上収益に関する数値または方針を確認。対象年度・単位・実績／目標の区分は原文を参照する。","progressAssessment":{"status":"not_comparable","reason":"JPX公式開示資料で計画・数値・方針を確認したが、自動抽出では目標と実績の同一定義・同一単位・同一企業範囲を最終確認できないため、単純な進捗率を作成しない。","sourceRef":"公式PDF p.5: 計画・成長戦略・財務目標・KPI・投資・株主還元に関する記載を確認する。"}},"reason":"守谷商会の公式計画と進捗評価を比較可能にする。","sourceUrl":"https://www2.jpx.co.jp/disc/17980/140120260512524177.pdf","sourcePage":"公式PDF p.5: 計画・成長戦略・財務目標・KPI・投資・株主還元に関する記載を確認する。 / 公式PDF p.1: 計画・成長戦略・財務目標・KPI・投資・株主還元に関する記載を確認する。 / 公式PDF p.14: 計画・成長戦略・財務目標・KPIに関する記載を確認する。","status":"corrected","reviewDecisionId":"review-1798-20260721-structured-expansion","detectedAt":"2026-07-21T13:03:00.000Z","correctedAt":"2026-07-21T13:33:00.000Z"},{"id":"correction-1799-20260721-structured-expansion","companyCode":"1799","fieldPath":"category,stage,tier,sourceUrl,document,period,planPublishedDate,lastVerifiedDate,themes,summary,revenue,profit,margin,capital,returnPolicy,highlights,warnings,evidenceRefs,flags,progressAssessment","before":{"stage":"jpx_indexed","pageEvidence":false,"planPublishedDate":null,"revenue":null,"progressAssessment":null},"after":{"stage":"detailed_extracted","pageEvidence":true,"planPublishedDate":"2026-05-14","revenue":"公式PDF p.17で売上高・売上収益に関する数値または方針を確認。対象年度・単位・実績／目標の区分は原文を参照する。","progressAssessment":{"status":"not_comparable","reason":"JPX公式開示資料で計画・数値・方針を確認したが、自動抽出では目標と実績の同一定義・同一単位・同一企業範囲を最終確認できないため、単純な進捗率を作成しない。","sourceRef":"公式PDF p.17: 財務目標・KPI・投資・株主還元に関する記載を確認する。"}},"reason":"第一建設工業の公式計画と進捗評価を比較可能にする。","sourceUrl":"https://www2.jpx.co.jp/disc/17990/140120260514535487.pdf","sourcePage":"公式PDF p.17: 財務目標・KPI・投資・株主還元に関する記載を確認する。 / 公式PDF p.3: 計画・成長戦略・財務目標・KPI・投資・株主還元に関する記載を確認する。 / 公式PDF p.18: 財務目標・KPI・投資・株主還元に関する記載を確認する。","status":"corrected","reviewDecisionId":"review-1799-20260721-structured-expansion","detectedAt":"2026-07-21T13:04:00.000Z","correctedAt":"2026-07-21T13:34:00.000Z"},{"id":"correction-1811-20260721-structured-expansion","companyCode":"1811","fieldPath":"category,stage,tier,sourceUrl,document,period,planPublishedDate,lastVerifiedDate,themes,summary,revenue,profit,margin,capital,returnPolicy,highlights,warnings,evidenceRefs,flags,progressAssessment","before":{"stage":"jpx_indexed","pageEvidence":false,"planPublishedDate":null,"revenue":null,"progressAssessment":null},"after":{"stage":"detailed_extracted","pageEvidence":true,"planPublishedDate":"2026-05-14","revenue":"公式PDF p.5で売上高・売上収益に関する数値または方針を確認。対象年度・単位・実績／目標の区分は原文を参照する。","progressAssessment":{"status":"not_comparable","reason":"JPX公式開示資料で計画・数値・方針を確認したが、自動抽出では目標と実績の同一定義・同一単位・同一企業範囲を最終確認できないため、単純な進捗率を作成しない。","sourceRef":"公式PDF p.4: 財務目標・KPIに関する記載を確認する。"}},"reason":"錢高組の公式計画と進捗評価を比較可能にする。","sourceUrl":"https://www2.jpx.co.jp/disc/18110/140120260513530654.pdf","sourcePage":"公式PDF p.4: 財務目標・KPIに関する記載を確認する。 / 公式PDF p.5: 財務目標・KPI・投資・株主還元に関する記載を確認する。 / 公式PDF p.1: 財務目標・KPI・投資・株主還元に関する記載を確認する。","status":"corrected","reviewDecisionId":"review-1811-20260721-structured-expansion","detectedAt":"2026-07-21T13:05:00.000Z","correctedAt":"2026-07-21T13:35:00.000Z"},{"id":"correction-1826-20260721-structured-expansion","companyCode":"1826","fieldPath":"category,stage,tier,sourceUrl,document,period,planPublishedDate,lastVerifiedDate,themes,summary,revenue,profit,margin,capital,returnPolicy,highlights,warnings,evidenceRefs,flags,progressAssessment","before":{"stage":"jpx_indexed","pageEvidence":false,"planPublishedDate":null,"revenue":null,"progressAssessment":null},"after":{"stage":"detailed_extracted","pageEvidence":true,"planPublishedDate":"2025-02-10","revenue":"公式PDF p.16で売上高・売上収益に関する数値または方針を確認。対象年度・単位・実績／目標の区分は原文を参照する。","progressAssessment":{"status":"not_comparable","reason":"JPX公式開示資料で計画・数値・方針を確認したが、自動抽出では目標と実績の同一定義・同一単位・同一企業範囲を最終確認できないため、単純な進捗率を作成しない。","sourceRef":"公式PDF p.26: 計画・成長戦略・財務目標・KPI・投資・株主還元に関する記載を確認する。"}},"reason":"佐田建設の公式計画と進捗評価を比較可能にする。","sourceUrl":"https://www2.jpx.co.jp/disc/18260/140120250207567265.pdf","sourcePage":"公式PDF p.26: 計画・成長戦略・財務目標・KPI・投資・株主還元に関する記載を確認する。 / 公式PDF p.12: 計画・成長戦略・財務目標・KPI・投資・株主還元に関する記載を確認する。 / 公式PDF p.1: 計画・成長戦略・財務目標・KPI・投資・株主還元に関する記載を確認する。","status":"corrected","reviewDecisionId":"review-1826-20260721-structured-expansion","detectedAt":"2026-07-21T13:06:00.000Z","correctedAt":"2026-07-21T13:36:00.000Z"},{"id":"correction-1828-20260721-structured-expansion","companyCode":"1828","fieldPath":"category,stage,tier,sourceUrl,document,period,planPublishedDate,lastVerifiedDate,themes,summary,revenue,profit,margin,capital,returnPolicy,highlights,warnings,evidenceRefs,flags,progressAssessment","before":{"stage":"jpx_indexed","pageEvidence":false,"planPublishedDate":null,"revenue":null,"progressAssessment":null},"after":{"stage":"detailed_extracted","pageEvidence":true,"planPublishedDate":"2024-11-06","revenue":"公式PDF p.13で売上高・売上収益に関する数値または方針を確認。対象年度・単位・実績／目標の区分は原文を参照する。","progressAssessment":{"status":"not_comparable","reason":"JPX公式開示資料で計画・数値・方針を確認したが、自動抽出では目標と実績の同一定義・同一単位・同一企業範囲を最終確認できないため、単純な進捗率を作成しない。","sourceRef":"公式PDF p.27: 計画・成長戦略・財務目標・KPI・投資・株主還元に関する記載を確認する。"}},"reason":"田辺工業の公式計画と進捗評価を比較可能にする。","sourceUrl":"https://www2.jpx.co.jp/disc/18280/140120241106512127.pdf","sourcePage":"公式PDF p.27: 計画・成長戦略・財務目標・KPI・投資・株主還元に関する記載を確認する。 / 公式PDF p.26: 計画・成長戦略・財務目標・KPIに関する記載を確認する。 / 公式PDF p.13: 計画・成長戦略・財務目標・KPIに関する記載を確認する。","status":"corrected","reviewDecisionId":"review-1828-20260721-structured-expansion","detectedAt":"2026-07-21T13:07:00.000Z","correctedAt":"2026-07-21T13:37:00.000Z"},{"id":"correction-274A-20260721-structured-expansion","companyCode":"274A","fieldPath":"category,stage,tier,sourceUrl,document,period,planPublishedDate,lastVerifiedDate,themes,summary,revenue,profit,margin,capital,returnPolicy,highlights,warnings,evidenceRefs,flags,progressAssessment","before":{"stage":"jpx_indexed","pageEvidence":false,"planPublishedDate":null,"revenue":null,"progressAssessment":null},"after":{"stage":"detailed_extracted","pageEvidence":true,"planPublishedDate":"2026-07-14","revenue":"公式PDF p.23で売上高・売上収益に関する数値または方針を確認。対象年度・単位・実績／目標の区分は原文を参照する。","progressAssessment":{"status":"not_comparable","reason":"JPX公式開示資料で計画・数値・方針を確認したが、自動抽出では目標と実績の同一定義・同一単位・同一企業範囲を最終確認できないため、単純な進捗率を作成しない。","sourceRef":"公式PDF p.23: 財務目標・KPI・投資・株主還元に関する記載を確認する。"}},"reason":"ガーデンの公式計画と進捗評価を比較可能にする。","sourceUrl":"https://www2.jpx.co.jp/disc/274A0/140120260714592925.pdf","sourcePage":"公式PDF p.23: 財務目標・KPI・投資・株主還元に関する記載を確認する。 / 公式PDF p.39: 計画・成長戦略・財務目標・KPIに関する記載を確認する。 / 公式PDF p.25: 財務目標・KPI・投資・株主還元に関する記載を確認する。","status":"corrected","reviewDecisionId":"review-274A-20260721-structured-expansion","detectedAt":"2026-07-21T13:08:00.000Z","correctedAt":"2026-07-21T13:38:00.000Z"},{"id":"correction-2762-20260721-structured-expansion","companyCode":"2762","fieldPath":"category,stage,tier,sourceUrl,document,period,planPublishedDate,lastVerifiedDate,themes,summary,revenue,profit,margin,capital,returnPolicy,highlights,warnings,evidenceRefs,flags,progressAssessment","before":{"stage":"jpx_indexed","pageEvidence":false,"planPublishedDate":null,"revenue":null,"progressAssessment":null},"after":{"stage":"detailed_extracted","pageEvidence":true,"planPublishedDate":"2023-08-28","revenue":"公式PDF p.26で売上高・売上収益に関する数値または方針を確認。対象年度・単位・実績／目標の区分は原文を参照する。","progressAssessment":{"status":"not_comparable","reason":"JPX公式開示資料で計画・数値・方針を確認したが、自動抽出では目標と実績の同一定義・同一単位・同一企業範囲を最終確認できないため、単純な進捗率を作成しない。","sourceRef":"公式PDF p.26: 計画・成長戦略・財務目標・KPIに関する記載を確認する。"}},"reason":"ＳＡＮＫＯ ＭＡＲＫＥＴＩＮＧ ＦＯＯＤＳの公式計画と進捗評価を比較可能にする。","sourceUrl":"https://www2.jpx.co.jp/disc/27620/140120230825546790.pdf","sourcePage":"公式PDF p.26: 計画・成長戦略・財務目標・KPIに関する記載を確認する。 / 公式PDF p.2: 計画・成長戦略・財務目標・KPIに関する記載を確認する。 / 公式PDF p.16: 計画・成長戦略に関する記載を確認する。","status":"corrected","reviewDecisionId":"review-2762-20260721-structured-expansion","detectedAt":"2026-07-21T13:09:00.000Z","correctedAt":"2026-07-21T13:39:00.000Z"},{"id":"correction-2764-20260721-structured-expansion","companyCode":"2764","fieldPath":"category,stage,tier,sourceUrl,document,period,planPublishedDate,lastVerifiedDate,themes,summary,revenue,profit,margin,capital,returnPolicy,highlights,warnings,evidenceRefs,flags,progressAssessment","before":{"stage":"jpx_indexed","pageEvidence":false,"planPublishedDate":null,"revenue":null,"progressAssessment":null},"after":{"stage":"detailed_extracted","pageEvidence":true,"planPublishedDate":"2026-02-26","revenue":"公式PDF p.51で売上高・売上収益に関する数値または方針を確認。対象年度・単位・実績／目標の区分は原文を参照する。","progressAssessment":{"status":"not_comparable","reason":"JPX公式開示資料で計画・数値・方針を確認したが、自動抽出では目標と実績の同一定義・同一単位・同一企業範囲を最終確認できないため、単純な進捗率を作成しない。","sourceRef":"公式PDF p.41: 計画・成長戦略・財務目標・KPIに関する記載を確認する。"}},"reason":"ひらまつの公式計画と進捗評価を比較可能にする。","sourceUrl":"https://www2.jpx.co.jp/disc/27640/140120260225568568.pdf","sourcePage":"公式PDF p.41: 計画・成長戦略・財務目標・KPIに関する記載を確認する。 / 公式PDF p.8: 計画・成長戦略・投資・株主還元に関する記載を確認する。 / 公式PDF p.2: 計画・成長戦略・財務目標・KPIに関する記載を確認する。","status":"corrected","reviewDecisionId":"review-2764-20260721-structured-expansion","detectedAt":"2026-07-21T13:10:00.000Z","correctedAt":"2026-07-21T13:40:00.000Z"},{"id":"correction-2769-20260721-structured-expansion","companyCode":"2769","fieldPath":"category,stage,tier,sourceUrl,document,period,planPublishedDate,lastVerifiedDate,themes,summary,revenue,profit,margin,capital,returnPolicy,highlights,warnings,evidenceRefs,flags,progressAssessment","before":{"stage":"jpx_indexed","pageEvidence":false,"planPublishedDate":null,"revenue":null,"progressAssessment":null},"after":{"stage":"detailed_extracted","pageEvidence":true,"planPublishedDate":"2026-07-10","revenue":"公式PDF p.6で売上高・売上収益に関する数値または方針を確認。対象年度・単位・実績／目標の区分は原文を参照する。","progressAssessment":{"status":"not_comparable","reason":"JPX公式開示資料で計画・数値・方針を確認したが、自動抽出では目標と実績の同一定義・同一単位・同一企業範囲を最終確認できないため、単純な進捗率を作成しない。","sourceRef":"公式PDF p.6: 財務目標・KPIに関する記載を確認する。"}},"reason":"ヴィレッジヴァンガードコーポレーションの公式計画と進捗評価を比較可能にする。","sourceUrl":"https://www2.jpx.co.jp/disc/27690/140120260709590829.pdf","sourcePage":"公式PDF p.6: 財務目標・KPIに関する記載を確認する。 / 公式PDF p.1: 財務目標・KPI・投資・株主還元に関する記載を確認する。 / 公式PDF p.16: 財務目標・KPIに関する記載を確認する。","status":"corrected","reviewDecisionId":"review-2769-20260721-structured-expansion","detectedAt":"2026-07-21T13:11:00.000Z","correctedAt":"2026-07-21T13:41:00.000Z"},{"id":"correction-2782-20260721-structured-expansion","companyCode":"2782","fieldPath":"category,stage,tier,sourceUrl,document,period,planPublishedDate,lastVerifiedDate,themes,summary,revenue,profit,margin,capital,returnPolicy,highlights,warnings,evidenceRefs,flags,progressAssessment","before":{"stage":"jpx_indexed","pageEvidence":false,"planPublishedDate":null,"revenue":null,"progressAssessment":null},"after":{"stage":"detailed_extracted","pageEvidence":true,"planPublishedDate":"2026-05-08","revenue":"公式PDF p.5で売上高・売上収益に関する数値または方針を確認。対象年度・単位・実績／目標の区分は原文を参照する。","progressAssessment":{"status":"not_comparable","reason":"JPX公式開示資料で計画・数値・方針を確認したが、自動抽出では目標と実績の同一定義・同一単位・同一企業範囲を最終確認できないため、単純な進捗率を作成しない。","sourceRef":"公式PDF p.5: 財務目標・KPI・投資・株主還元に関する記載を確認する。"}},"reason":"セリアの公式計画と進捗評価を比較可能にする。","sourceUrl":"https://www2.jpx.co.jp/disc/27820/140120260507518675.pdf","sourcePage":"公式PDF p.5: 財務目標・KPI・投資・株主還元に関する記載を確認する。 / 公式PDF p.1: 財務目標・KPI・投資・株主還元に関する記載を確認する。 / 公式PDF p.9: 財務目標・KPI・投資・株主還元に関する記載を確認する。","status":"corrected","reviewDecisionId":"review-2782-20260721-structured-expansion","detectedAt":"2026-07-21T13:12:00.000Z","correctedAt":"2026-07-21T13:42:00.000Z"},{"id":"correction-2789-20260721-structured-expansion","companyCode":"2789","fieldPath":"category,stage,tier,sourceUrl,document,period,planPublishedDate,lastVerifiedDate,themes,summary,revenue,profit,margin,capital,returnPolicy,highlights,warnings,evidenceRefs,flags,progressAssessment","before":{"stage":"jpx_indexed","pageEvidence":false,"planPublishedDate":null,"revenue":null,"progressAssessment":null},"after":{"stage":"detailed_extracted","pageEvidence":true,"planPublishedDate":"2026-07-06","revenue":"公式PDF p.4で売上高・売上収益に関する数値または方針を確認。対象年度・単位・実績／目標の区分は原文を参照する。","progressAssessment":{"status":"not_comparable","reason":"JPX公式開示資料で計画・数値・方針を確認したが、自動抽出では目標と実績の同一定義・同一単位・同一企業範囲を最終確認できないため、単純な進捗率を作成しない。","sourceRef":"公式PDF p.4: 財務目標・KPI・投資・株主還元に関する記載を確認する。"}},"reason":"カルラの公式計画と進捗評価を比較可能にする。","sourceUrl":"https://www2.jpx.co.jp/disc/27890/140120260703587519.pdf","sourcePage":"公式PDF p.4: 財務目標・KPI・投資・株主還元に関する記載を確認する。 / 公式PDF p.1: 財務目標・KPI・投資・株主還元に関する記載を確認する。 / 公式PDF p.8: 財務目標・KPIに関する記載を確認する。","status":"corrected","reviewDecisionId":"review-2789-20260721-structured-expansion","detectedAt":"2026-07-21T13:13:00.000Z","correctedAt":"2026-07-21T13:43:00.000Z"},{"id":"correction-2790-20260721-structured-expansion","companyCode":"2790","fieldPath":"category,stage,tier,sourceUrl,document,period,planPublishedDate,lastVerifiedDate,themes,summary,revenue,profit,margin,capital,returnPolicy,highlights,warnings,evidenceRefs,flags,progressAssessment","before":{"stage":"jpx_indexed","pageEvidence":false,"planPublishedDate":null,"revenue":null,"progressAssessment":null},"after":{"stage":"detailed_extracted","pageEvidence":true,"planPublishedDate":"2026-05-11","revenue":"公式PDF p.23で売上高・売上収益に関する数値または方針を確認。対象年度・単位・実績／目標の区分は原文を参照する。","progressAssessment":{"status":"not_comparable","reason":"JPX公式開示資料で計画・数値・方針を確認したが、自動抽出では目標と実績の同一定義・同一単位・同一企業範囲を最終確認できないため、単純な進捗率を作成しない。","sourceRef":"公式PDF p.26: 財務目標・KPIに関する記載を確認する。"}},"reason":"ナフコの公式計画と進捗評価を比較可能にする。","sourceUrl":"https://www2.jpx.co.jp/disc/27900/140120260511521430.pdf","sourcePage":"公式PDF p.26: 財務目標・KPIに関する記載を確認する。 / 公式PDF p.25: 財務目標・KPIに関する記載を確認する。 / 公式PDF p.23: 財務目標・KPIに関する記載を確認する。","status":"corrected","reviewDecisionId":"review-2790-20260721-structured-expansion","detectedAt":"2026-07-21T13:14:00.000Z","correctedAt":"2026-07-21T13:44:00.000Z"},{"id":"correction-2798-20260721-structured-expansion","companyCode":"2798","fieldPath":"category,stage,tier,sourceUrl,document,period,planPublishedDate,lastVerifiedDate,themes,summary,revenue,profit,margin,capital,returnPolicy,highlights,warnings,evidenceRefs,flags,progressAssessment","before":{"stage":"jpx_indexed","pageEvidence":false,"planPublishedDate":null,"revenue":null,"progressAssessment":null},"after":{"stage":"detailed_extracted","pageEvidence":true,"planPublishedDate":"2026-04-22","revenue":"公式PDF p.4で売上高・売上収益に関する数値または方針を確認。対象年度・単位・実績／目標の区分は原文を参照する。","progressAssessment":{"status":"not_comparable","reason":"JPX公式開示資料で計画・数値・方針を確認したが、自動抽出では目標と実績の同一定義・同一単位・同一企業範囲を最終確認できないため、単純な進捗率を作成しない。","sourceRef":"公式PDF p.7: 財務目標・KPIに関する記載を確認する。"}},"reason":"ワイズテーブルコーポレーションの公式計画と進捗評価を比較可能にする。","sourceUrl":"https://www2.jpx.co.jp/disc/27980/140120260422508092.pdf","sourcePage":"公式PDF p.7: 財務目標・KPIに関する記載を確認する。 / 公式PDF p.4: 財務目標・KPIに関する記載を確認する。 / 公式PDF p.15: 財務目標・KPIに関する記載を確認する。","status":"corrected","reviewDecisionId":"review-2798-20260721-structured-expansion","detectedAt":"2026-07-21T13:15:00.000Z","correctedAt":"2026-07-21T13:45:00.000Z"},{"id":"correction-2805-20260721-structured-expansion","companyCode":"2805","fieldPath":"category,stage,tier,sourceUrl,document,period,planPublishedDate,lastVerifiedDate,themes,summary,revenue,profit,margin,capital,returnPolicy,highlights,warnings,evidenceRefs,flags,progressAssessment","before":{"stage":"jpx_indexed","pageEvidence":false,"planPublishedDate":null,"revenue":null,"progressAssessment":null},"after":{"stage":"detailed_extracted","pageEvidence":true,"planPublishedDate":"2026-05-13","revenue":"公式PDF p.24で売上高・売上収益に関する数値または方針を確認。対象年度・単位・実績／目標の区分は原文を参照する。","progressAssessment":{"status":"not_comparable","reason":"JPX公式開示資料で計画・数値・方針を確認したが、自動抽出では目標と実績の同一定義・同一単位・同一企業範囲を最終確認できないため、単純な進捗率を作成しない。","sourceRef":"公式PDF p.24: 財務目標・KPI・投資・株主還元に関する記載を確認する。"}},"reason":"ヱスビー食品の公式計画と進捗評価を比較可能にする。","sourceUrl":"https://www2.jpx.co.jp/disc/28050/140120260512527375.pdf","sourcePage":"公式PDF p.24: 財務目標・KPI・投資・株主還元に関する記載を確認する。 / 公式PDF p.14: 財務目標・KPIに関する記載を確認する。 / 公式PDF p.17: 計画・成長戦略・財務目標・KPI・投資・株主還元に関する記載を確認する。","status":"corrected","reviewDecisionId":"review-2805-20260721-structured-expansion","detectedAt":"2026-07-21T13:16:00.000Z","correctedAt":"2026-07-21T13:46:00.000Z"},{"id":"correction-2806-20260721-structured-expansion","companyCode":"2806","fieldPath":"category,stage,tier,sourceUrl,document,period,planPublishedDate,lastVerifiedDate,themes,summary,revenue,profit,margin,capital,returnPolicy,highlights,warnings,evidenceRefs,flags,progressAssessment","before":{"stage":"jpx_indexed","pageEvidence":false,"planPublishedDate":null,"revenue":null,"progressAssessment":null},"after":{"stage":"detailed_extracted","pageEvidence":true,"planPublishedDate":"2026-05-15","revenue":"公式PDF p.5で売上高・売上収益に関する数値または方針を確認。対象年度・単位・実績／目標の区分は原文を参照する。","progressAssessment":{"status":"not_comparable","reason":"JPX公式開示資料で計画・数値・方針を確認したが、自動抽出では目標と実績の同一定義・同一単位・同一企業範囲を最終確認できないため、単純な進捗率を作成しない。","sourceRef":"公式PDF p.5: 計画・成長戦略・財務目標・KPIに関する記載を確認する。"}},"reason":"ユタカフーズの公式計画と進捗評価を比較可能にする。","sourceUrl":"https://www2.jpx.co.jp/disc/28060/140120260426511000.pdf","sourcePage":"公式PDF p.5: 計画・成長戦略・財務目標・KPIに関する記載を確認する。 / 公式PDF p.4: 財務目標・KPI・投資・株主還元に関する記載を確認する。 / 公式PDF p.17: 財務目標・KPIに関する記載を確認する。","status":"corrected","reviewDecisionId":"review-2806-20260721-structured-expansion","detectedAt":"2026-07-21T13:17:00.000Z","correctedAt":"2026-07-21T13:47:00.000Z"},{"id":"correction-2813-20260721-structured-expansion","companyCode":"2813","fieldPath":"category,stage,tier,sourceUrl,document,period,planPublishedDate,lastVerifiedDate,themes,summary,revenue,profit,margin,capital,returnPolicy,highlights,warnings,evidenceRefs,flags,progressAssessment","before":{"stage":"jpx_indexed","pageEvidence":false,"planPublishedDate":null,"revenue":null,"progressAssessment":null},"after":{"stage":"detailed_extracted","pageEvidence":true,"planPublishedDate":"2026-03-13","revenue":"公式PDF p.17で売上高・売上収益に関する数値または方針を確認。対象年度・単位・実績／目標の区分は原文を参照する。","progressAssessment":{"status":"not_comparable","reason":"JPX公式開示資料で計画・数値・方針を確認したが、自動抽出では目標と実績の同一定義・同一単位・同一企業範囲を最終確認できないため、単純な進捗率を作成しない。","sourceRef":"公式PDF p.17: 計画・成長戦略・財務目標・KPIに関する記載を確認する。"}},"reason":"和弘食品の公式計画と進捗評価を比較可能にする。","sourceUrl":"https://www2.jpx.co.jp/disc/28130/140120260310578824.pdf","sourcePage":"公式PDF p.17: 計画・成長戦略・財務目標・KPIに関する記載を確認する。 / 公式PDF p.9: 計画・成長戦略・財務目標・KPIに関する記載を確認する。 / 公式PDF p.18: 計画・成長戦略・財務目標・KPIに関する記載を確認する。","status":"corrected","reviewDecisionId":"review-2813-20260721-structured-expansion","detectedAt":"2026-07-21T13:18:00.000Z","correctedAt":"2026-07-21T13:48:00.000Z"},{"id":"correction-2814-20260721-structured-expansion","companyCode":"2814","fieldPath":"category,stage,tier,sourceUrl,document,period,planPublishedDate,lastVerifiedDate,themes,summary,revenue,profit,margin,capital,returnPolicy,highlights,warnings,evidenceRefs,flags,progressAssessment","before":{"stage":"jpx_indexed","pageEvidence":false,"planPublishedDate":null,"revenue":null,"progressAssessment":null},"after":{"stage":"detailed_extracted","pageEvidence":true,"planPublishedDate":"2025-05-22","revenue":"公式PDF p.2で売上高・売上収益に関する数値または方針を確認。対象年度・単位・実績／目標の区分は原文を参照する。","progressAssessment":{"status":"not_comparable","reason":"JPX公式開示資料で計画・数値・方針を確認したが、自動抽出では目標と実績の同一定義・同一単位・同一企業範囲を最終確認できないため、単純な進捗率を作成しない。","sourceRef":"公式PDF p.2: 計画・成長戦略・財務目標・KPIに関する記載を確認する。"}},"reason":"佐藤食品工業の公式計画と進捗評価を比較可能にする。","sourceUrl":"https://www2.jpx.co.jp/disc/28140/140120250522562425.pdf","sourcePage":"公式PDF p.2: 計画・成長戦略・財務目標・KPIに関する記載を確認する。 / 公式PDF p.1: 計画・成長戦略に関する記載を確認する。","status":"corrected","reviewDecisionId":"review-2814-20260721-structured-expansion","detectedAt":"2026-07-21T13:19:00.000Z","correctedAt":"2026-07-21T13:49:00.000Z"},{"id":"correction-2816-20260721-structured-expansion","companyCode":"2816","fieldPath":"category,stage,tier,sourceUrl,document,period,planPublishedDate,lastVerifiedDate,themes,summary,revenue,profit,margin,capital,returnPolicy,highlights,warnings,evidenceRefs,flags,progressAssessment","before":{"stage":"jpx_indexed","pageEvidence":false,"planPublishedDate":null,"revenue":null,"progressAssessment":null},"after":{"stage":"detailed_extracted","pageEvidence":true,"planPublishedDate":"2026-05-11","revenue":"公式PDF p.4で売上高・売上収益に関する数値または方針を確認。対象年度・単位・実績／目標の区分は原文を参照する。","progressAssessment":{"status":"not_comparable","reason":"JPX公式開示資料で計画・数値・方針を確認したが、自動抽出では目標と実績の同一定義・同一単位・同一企業範囲を最終確認できないため、単純な進捗率を作成しない。","sourceRef":"公式PDF p.6: 計画・成長戦略・財務目標・KPI・投資・株主還元に関する記載を確認する。"}},"reason":"ダイショーの公式計画と進捗評価を比較可能にする。","sourceUrl":"https://www2.jpx.co.jp/disc/28160/140120260508519806.pdf","sourcePage":"公式PDF p.6: 計画・成長戦略・財務目標・KPI・投資・株主還元に関する記載を確認する。 / 公式PDF p.4: 計画・成長戦略・財務目標・KPIに関する記載を確認する。 / 公式PDF p.1: 財務目標・KPI・投資・株主還元に関する記載を確認する。","status":"corrected","reviewDecisionId":"review-2816-20260721-structured-expansion","detectedAt":"2026-07-21T13:20:00.000Z","correctedAt":"2026-07-21T13:50:00.000Z"},{"id":"correction-2820-20260721-structured-expansion","companyCode":"2820","fieldPath":"category,stage,tier,sourceUrl,document,period,planPublishedDate,lastVerifiedDate,themes,summary,revenue,profit,margin,capital,returnPolicy,highlights,warnings,evidenceRefs,flags,progressAssessment","before":{"stage":"jpx_indexed","pageEvidence":false,"planPublishedDate":null,"revenue":null,"progressAssessment":null},"after":{"stage":"detailed_extracted","pageEvidence":true,"planPublishedDate":"2025-08-14","revenue":"公式PDF p.2で売上高・売上収益に関する数値または方針を確認。対象年度・単位・実績／目標の区分は原文を参照する。","progressAssessment":{"status":"not_comparable","reason":"JPX公式開示資料で計画・数値・方針を確認したが、自動抽出では目標と実績の同一定義・同一単位・同一企業範囲を最終確認できないため、単純な進捗率を作成しない。","sourceRef":"公式PDF p.2: 計画・成長戦略・財務目標・KPIに関する記載を確認する。"}},"reason":"やまみの公式計画と進捗評価を比較可能にする。","sourceUrl":"https://www2.jpx.co.jp/disc/28200/140120250813540632.pdf","sourcePage":"公式PDF p.2: 計画・成長戦略・財務目標・KPIに関する記載を確認する。 / 公式PDF p.1: 計画・成長戦略・財務目標・KPIに関する記載を確認する。","status":"corrected","reviewDecisionId":"review-2820-20260721-structured-expansion","detectedAt":"2026-07-21T13:21:00.000Z","correctedAt":"2026-07-21T13:51:00.000Z"},{"id":"correction-2831-20260721-structured-expansion","companyCode":"2831","fieldPath":"category,stage,tier,sourceUrl,document,period,planPublishedDate,lastVerifiedDate,themes,summary,revenue,profit,margin,capital,returnPolicy,highlights,warnings,evidenceRefs,flags,progressAssessment","before":{"stage":"jpx_indexed","pageEvidence":false,"planPublishedDate":null,"revenue":null,"progressAssessment":null},"after":{"stage":"detailed_extracted","pageEvidence":true,"planPublishedDate":"2026-05-13","revenue":"公式PDF p.4で売上高・売上収益に関する数値または方針を確認。対象年度・単位・実績／目標の区分は原文を参照する。","progressAssessment":{"status":"not_comparable","reason":"JPX公式開示資料で計画・数値・方針を確認したが、自動抽出では目標と実績の同一定義・同一単位・同一企業範囲を最終確認できないため、単純な進捗率を作成しない。","sourceRef":"公式PDF p.4: 計画・成長戦略・財務目標・KPIに関する記載を確認する。"}},"reason":"はごろもフーズの公式計画と進捗評価を比較可能にする。","sourceUrl":"https://www2.jpx.co.jp/disc/28310/140120260513527630.pdf","sourcePage":"公式PDF p.4: 計画・成長戦略・財務目標・KPIに関する記載を確認する。 / 公式PDF p.3: 計画・成長戦略・財務目標・KPI・投資・株主還元に関する記載を確認する。 / 公式PDF p.2: 財務目標・KPIに関する記載を確認する。","status":"corrected","reviewDecisionId":"review-2831-20260721-structured-expansion","detectedAt":"2026-07-21T13:22:00.000Z","correctedAt":"2026-07-21T13:52:00.000Z"},{"id":"correction-2872-20260721-structured-expansion","companyCode":"2872","fieldPath":"category,stage,tier,sourceUrl,document,period,planPublishedDate,lastVerifiedDate,themes,summary,revenue,profit,margin,capital,returnPolicy,highlights,warnings,evidenceRefs,flags,progressAssessment","before":{"stage":"jpx_indexed","pageEvidence":false,"planPublishedDate":null,"revenue":null,"progressAssessment":null},"after":{"stage":"detailed_extracted","pageEvidence":true,"planPublishedDate":"2026-04-17","revenue":"公式PDF p.2で売上高・売上収益に関する数値または方針を確認。対象年度・単位・実績／目標の区分は原文を参照する。","progressAssessment":{"status":"not_comparable","reason":"JPX公式開示資料で計画・数値・方針を確認したが、自動抽出では目標と実績の同一定義・同一単位・同一企業範囲を最終確認できないため、単純な進捗率を作成しない。","sourceRef":"公式PDF p.2: 計画・成長戦略・財務目標・KPI・投資・株主還元に関する記載を確認する。"}},"reason":"セイヒョーの公式計画と進捗評価を比較可能にする。","sourceUrl":"https://www2.jpx.co.jp/disc/28720/140120260417505994.pdf","sourcePage":"公式PDF p.2: 計画・成長戦略・財務目標・KPI・投資・株主還元に関する記載を確認する。 / 公式PDF p.5: 計画・成長戦略・財務目標・KPIに関する記載を確認する。 / 公式PDF p.1: 計画・成長戦略・財務目標・KPIに関する記載を確認する。","status":"corrected","reviewDecisionId":"review-2872-20260721-structured-expansion","detectedAt":"2026-07-21T13:23:00.000Z","correctedAt":"2026-07-21T13:53:00.000Z"},{"id":"correction-2876-20260721-structured-expansion","companyCode":"2876","fieldPath":"category,stage,tier,sourceUrl,document,period,planPublishedDate,lastVerifiedDate,themes,summary,revenue,profit,margin,capital,returnPolicy,highlights,warnings,evidenceRefs,flags,progressAssessment","before":{"stage":"jpx_indexed","pageEvidence":false,"planPublishedDate":null,"revenue":null,"progressAssessment":null},"after":{"stage":"detailed_extracted","pageEvidence":true,"planPublishedDate":"2023-05-15","revenue":"公式PDF p.8で売上高・売上収益に関する数値または方針を確認。対象年度・単位・実績／目標の区分は原文を参照する。","progressAssessment":{"status":"not_comparable","reason":"JPX公式開示資料で計画・数値・方針を確認したが、自動抽出では目標と実績の同一定義・同一単位・同一企業範囲を最終確認できないため、単純な進捗率を作成しない。","sourceRef":"公式PDF p.8: 計画・成長戦略・財務目標・KPIに関する記載を確認する。"}},"reason":"デルソーレの公式計画と進捗評価を比較可能にする。","sourceUrl":"https://www2.jpx.co.jp/disc/28760/140120230510564064.pdf","sourcePage":"公式PDF p.8: 計画・成長戦略・財務目標・KPIに関する記載を確認する。 / 公式PDF p.2: 計画・成長戦略・財務目標・KPI・投資・株主還元に関する記載を確認する。 / 公式PDF p.17: 財務目標・KPIに関する記載を確認する。","status":"corrected","reviewDecisionId":"review-2876-20260721-structured-expansion","detectedAt":"2026-07-21T13:24:00.000Z","correctedAt":"2026-07-21T13:54:00.000Z"},{"id":"correction-2877-20260721-structured-expansion","companyCode":"2877","fieldPath":"category,stage,tier,sourceUrl,document,period,planPublishedDate,lastVerifiedDate,themes,summary,revenue,profit,margin,capital,returnPolicy,highlights,warnings,evidenceRefs,flags,progressAssessment","before":{"stage":"jpx_indexed","pageEvidence":false,"planPublishedDate":null,"revenue":null,"progressAssessment":null},"after":{"stage":"detailed_extracted","pageEvidence":true,"planPublishedDate":"2024-11-12","revenue":"公式PDF p.9で売上高・売上収益に関する数値または方針を確認。対象年度・単位・実績／目標の区分は原文を参照する。","progressAssessment":{"status":"not_comparable","reason":"JPX公式開示資料で計画・数値・方針を確認したが、自動抽出では目標と実績の同一定義・同一単位・同一企業範囲を最終確認できないため、単純な進捗率を作成しない。","sourceRef":"公式PDF p.16: 計画・成長戦略・財務目標・KPI・投資・株主還元に関する記載を確認する。"}},"reason":"日東ベストの公式計画と進捗評価を比較可能にする。","sourceUrl":"https://www2.jpx.co.jp/disc/28770/140120240926588957.pdf","sourcePage":"公式PDF p.16: 計画・成長戦略・財務目標・KPI・投資・株主還元に関する記載を確認する。 / 公式PDF p.9: 計画・成長戦略・財務目標・KPIに関する記載を確認する。 / 公式PDF p.12: 計画・成長戦略・財務目標・KPIに関する記載を確認する。","status":"corrected","reviewDecisionId":"review-2877-20260721-structured-expansion","detectedAt":"2026-07-21T13:25:00.000Z","correctedAt":"2026-07-21T13:55:00.000Z"},{"id":"correction-3299-20260721-structured-expansion","companyCode":"3299","fieldPath":"category,stage,tier,sourceUrl,document,period,planPublishedDate,lastVerifiedDate,themes,summary,revenue,profit,margin,capital,returnPolicy,highlights,warnings,evidenceRefs,flags,progressAssessment","before":{"stage":"jpx_indexed","pageEvidence":false,"planPublishedDate":null,"revenue":null,"progressAssessment":null},"after":{"stage":"detailed_extracted","pageEvidence":true,"planPublishedDate":"2025-02-14","revenue":"公式PDF p.11で売上高・売上収益に関する数値または方針を確認。対象年度・単位・実績／目標の区分は原文を参照する。","progressAssessment":{"status":"not_comparable","reason":"JPX公式開示資料で計画・数値・方針を確認したが、自動抽出では目標と実績の同一定義・同一単位・同一企業範囲を最終確認できないため、単純な進捗率を作成しない。","sourceRef":"公式PDF p.37: 計画・成長戦略・財務目標・KPI・投資・株主還元に関する記載を確認する。"}},"reason":"ムゲンエステートの公式計画と進捗評価を比較可能にする。","sourceUrl":"https://www2.jpx.co.jp/disc/32990/140120250213572210.pdf","sourcePage":"公式PDF p.37: 計画・成長戦略・財務目標・KPI・投資・株主還元に関する記載を確認する。 / 公式PDF p.11: 計画・成長戦略・財務目標・KPI・投資・株主還元に関する記載を確認する。 / 公式PDF p.24: 計画・成長戦略・財務目標・KPI・投資・株主還元に関する記載を確認する。","status":"corrected","reviewDecisionId":"review-3299-20260721-structured-expansion","detectedAt":"2026-07-21T13:26:00.000Z","correctedAt":"2026-07-21T13:56:00.000Z"},{"id":"correction-3452-20260721-structured-expansion","companyCode":"3452","fieldPath":"category,stage,tier,sourceUrl,document,period,planPublishedDate,lastVerifiedDate,themes,summary,revenue,profit,margin,capital,returnPolicy,highlights,warnings,evidenceRefs,flags,progressAssessment","before":{"stage":"jpx_indexed","pageEvidence":false,"planPublishedDate":null,"revenue":null,"progressAssessment":null},"after":{"stage":"detailed_extracted","pageEvidence":true,"planPublishedDate":"2025-04-30","revenue":"公式PDF p.17で売上高・売上収益に関する数値または方針を確認。対象年度・単位・実績／目標の区分は原文を参照する。","progressAssessment":{"status":"not_comparable","reason":"JPX公式開示資料で計画・数値・方針を確認したが、自動抽出では目標と実績の同一定義・同一単位・同一企業範囲を最終確認できないため、単純な進捗率を作成しない。","sourceRef":"公式PDF p.2: 計画・成長戦略・財務目標・KPIに関する記載を確認する。"}},"reason":"ビーロットの公式計画と進捗評価を比較可能にする。","sourceUrl":"https://www2.jpx.co.jp/disc/34520/140120250430527528.pdf","sourcePage":"公式PDF p.2: 計画・成長戦略・財務目標・KPIに関する記載を確認する。 / 公式PDF p.17: 財務目標・KPI・投資・株主還元に関する記載を確認する。 / 公式PDF p.39: 計画・成長戦略・財務目標・KPIに関する記載を確認する。","status":"corrected","reviewDecisionId":"review-3452-20260721-structured-expansion","detectedAt":"2026-07-21T13:27:00.000Z","correctedAt":"2026-07-21T13:57:00.000Z"},{"id":"correction-3454-20260721-structured-expansion","companyCode":"3454","fieldPath":"category,stage,tier,sourceUrl,document,period,planPublishedDate,lastVerifiedDate,themes,summary,revenue,profit,margin,capital,returnPolicy,highlights,warnings,evidenceRefs,flags,progressAssessment","before":{"stage":"jpx_indexed","pageEvidence":false,"planPublishedDate":null,"revenue":null,"progressAssessment":null},"after":{"stage":"detailed_extracted","pageEvidence":true,"planPublishedDate":"2026-07-10","revenue":"公式PDF p.29で売上高・売上収益に関する数値または方針を確認。対象年度・単位・実績／目標の区分は原文を参照する。","progressAssessment":{"status":"not_comparable","reason":"JPX公式開示資料で計画・数値・方針を確認したが、自動抽出では目標と実績の同一定義・同一単位・同一企業範囲を最終確認できないため、単純な進捗率を作成しない。","sourceRef":"公式PDF p.5: 財務目標・KPI・投資・株主還元に関する記載を確認する。"}},"reason":"ファーストブラザーズの公式計画と進捗評価を比較可能にする。","sourceUrl":"https://www2.jpx.co.jp/disc/34540/140120260710591583.pdf","sourcePage":"公式PDF p.5: 財務目標・KPI・投資・株主還元に関する記載を確認する。 / 公式PDF p.30: 財務目標・KPIに関する記載を確認する。 / 公式PDF p.29: 財務目標・KPIに関する記載を確認する。","status":"corrected","reviewDecisionId":"review-3454-20260721-structured-expansion","detectedAt":"2026-07-21T13:28:00.000Z","correctedAt":"2026-07-21T13:58:00.000Z"},{"id":"correction-3461-20260721-structured-expansion","companyCode":"3461","fieldPath":"category,stage,tier,sourceUrl,document,period,planPublishedDate,lastVerifiedDate,themes,summary,revenue,profit,margin,capital,returnPolicy,highlights,warnings,evidenceRefs,flags,progressAssessment","before":{"stage":"jpx_indexed","pageEvidence":false,"planPublishedDate":null,"revenue":null,"progressAssessment":null},"after":{"stage":"detailed_extracted","pageEvidence":true,"planPublishedDate":"2025-02-07","revenue":"固定の中期売上高・売上収益は当該公式資料の抽出範囲で確認できない。","progressAssessment":{"status":"not_comparable","reason":"JPX公式開示資料で計画・数値・方針を確認したが、自動抽出では目標と実績の同一定義・同一単位・同一企業範囲を最終確認できないため、単純な進捗率を作成しない。","sourceRef":"公式PDF p.5: 計画・成長戦略・財務目標・KPI・投資・株主還元に関する記載を確認する。"}},"reason":"パルマの公式計画と進捗評価を比較可能にする。","sourceUrl":"https://www2.jpx.co.jp/disc/34610/140120250206565164.pdf","sourcePage":"公式PDF p.5: 計画・成長戦略・財務目標・KPI・投資・株主還元に関する記載を確認する。 / 公式PDF p.25: 計画・成長戦略・投資・株主還元に関する記載を確認する。 / 公式PDF p.2: 財務目標・KPI・投資・株主還元に関する記載を確認する。","status":"corrected","reviewDecisionId":"review-3461-20260721-structured-expansion","detectedAt":"2026-07-21T13:29:00.000Z","correctedAt":"2026-07-21T13:59:00.000Z"},{"id":"correction-3467-20260721-structured-expansion","companyCode":"3467","fieldPath":"category,stage,tier,sourceUrl,document,period,planPublishedDate,lastVerifiedDate,themes,summary,revenue,profit,margin,capital,returnPolicy,highlights,warnings,evidenceRefs,flags,progressAssessment","before":{"stage":"jpx_indexed","pageEvidence":false,"planPublishedDate":null,"revenue":null,"progressAssessment":null},"after":{"stage":"detailed_extracted","pageEvidence":true,"planPublishedDate":"2022-05-06","revenue":"公式PDF p.14で売上高・売上収益に関する数値または方針を確認。対象年度・単位・実績／目標の区分は原文を参照する。","progressAssessment":{"status":"not_comparable","reason":"JPX公式開示資料で計画・数値・方針を確認したが、自動抽出では目標と実績の同一定義・同一単位・同一企業範囲を最終確認できないため、単純な進捗率を作成しない。","sourceRef":"公式PDF p.2: 計画・成長戦略・投資・株主還元に関する記載を確認する。"}},"reason":"アグレ都市デザインの公式計画と進捗評価を比較可能にする。","sourceUrl":"https://www2.jpx.co.jp/disc/34670/140120220502533144.pdf","sourcePage":"公式PDF p.2: 計画・成長戦略・投資・株主還元に関する記載を確認する。 / 公式PDF p.14: 財務目標・KPIに関する記載を確認する。 / 公式PDF p.6: 財務目標・KPIに関する記載を確認する。","status":"corrected","reviewDecisionId":"review-3467-20260721-structured-expansion","detectedAt":"2026-07-21T13:30:00.000Z","correctedAt":"2026-07-21T14:00:00.000Z"},{"id":"correction-3607-20260721-structured-expansion","companyCode":"3607","fieldPath":"category,stage,tier,sourceUrl,document,period,planPublishedDate,lastVerifiedDate,themes,summary,revenue,profit,margin,capital,returnPolicy,highlights,warnings,evidenceRefs,flags,progressAssessment","before":{"stage":"jpx_indexed","pageEvidence":false,"planPublishedDate":null,"revenue":null,"progressAssessment":null},"after":{"stage":"detailed_extracted","pageEvidence":true,"planPublishedDate":"2026-06-30","revenue":"公式PDF p.1で売上高・売上収益に関する数値または方針を確認。対象年度・単位・実績／目標の区分は原文を参照する。","progressAssessment":{"status":"not_comparable","reason":"JPX公式開示資料で計画・数値・方針を確認したが、自動抽出では目標と実績の同一定義・同一単位・同一企業範囲を最終確認できないため、単純な進捗率を作成しない。","sourceRef":"公式PDF p.1: 財務目標・KPI・投資・株主還元に関する記載を確認する。"}},"reason":"クラウディアホールディングスの公式計画と進捗評価を比較可能にする。","sourceUrl":"https://www2.jpx.co.jp/disc/36070/140120260629582983.pdf","sourcePage":"公式PDF p.1: 財務目標・KPI・投資・株主還元に関する記載を確認する。 / 公式PDF p.8: 財務目標・KPI・投資・株主還元に関する記載を確認する。 / 公式PDF p.5: 財務目標・KPIに関する記載を確認する。","status":"corrected","reviewDecisionId":"review-3607-20260721-structured-expansion","detectedAt":"2026-07-21T13:31:00.000Z","correctedAt":"2026-07-21T14:01:00.000Z"},{"id":"correction-3611-20260721-structured-expansion","companyCode":"3611","fieldPath":"category,stage,tier,sourceUrl,document,period,planPublishedDate,lastVerifiedDate,themes,summary,revenue,profit,margin,capital,returnPolicy,highlights,warnings,evidenceRefs,flags,progressAssessment","before":{"stage":"jpx_indexed","pageEvidence":false,"planPublishedDate":null,"revenue":null,"progressAssessment":null},"after":{"stage":"detailed_extracted","pageEvidence":true,"planPublishedDate":"2025-11-13","revenue":"公式PDF p.15で売上高・売上収益に関する数値または方針を確認。対象年度・単位・実績／目標の区分は原文を参照する。","progressAssessment":{"status":"not_comparable","reason":"JPX公式開示資料で計画・数値・方針を確認したが、自動抽出では目標と実績の同一定義・同一単位・同一企業範囲を最終確認できないため、単純な進捗率を作成しない。","sourceRef":"公式PDF p.15: 計画・成長戦略・財務目標・KPIに関する記載を確認する。"}},"reason":"マツオカコーポレーションの公式計画と進捗評価を比較可能にする。","sourceUrl":"https://www2.jpx.co.jp/disc/36110/140120251113500241.pdf","sourcePage":"公式PDF p.15: 計画・成長戦略・財務目標・KPIに関する記載を確認する。 / 公式PDF p.14: 計画・成長戦略・財務目標・KPIに関する記載を確認する。 / 公式PDF p.28: 計画・成長戦略・財務目標・KPIに関する記載を確認する。","status":"corrected","reviewDecisionId":"review-3611-20260721-structured-expansion","detectedAt":"2026-07-21T13:32:00.000Z","correctedAt":"2026-07-21T14:02:00.000Z"},{"id":"correction-365A-20260721-structured-expansion","companyCode":"365A","fieldPath":"category,stage,tier,sourceUrl,document,period,planPublishedDate,lastVerifiedDate,themes,summary,revenue,profit,margin,capital,returnPolicy,highlights,warnings,evidenceRefs,flags,progressAssessment","before":{"stage":"jpx_indexed","pageEvidence":false,"planPublishedDate":null,"revenue":null,"progressAssessment":null},"after":{"stage":"detailed_extracted","pageEvidence":true,"planPublishedDate":"2026-07-14","revenue":"公式PDF p.4で売上高・売上収益に関する数値または方針を確認。対象年度・単位・実績／目標の区分は原文を参照する。","progressAssessment":{"status":"not_comparable","reason":"JPX公式開示資料で計画・数値・方針を確認したが、自動抽出では目標と実績の同一定義・同一単位・同一企業範囲を最終確認できないため、単純な進捗率を作成しない。","sourceRef":"公式PDF p.4: 財務目標・KPIに関する記載を確認する。"}},"reason":"伊澤タオルの公式計画と進捗評価を比較可能にする。","sourceUrl":"https://www2.jpx.co.jp/disc/365A0/140120260714593357.pdf","sourcePage":"公式PDF p.4: 財務目標・KPIに関する記載を確認する。 / 公式PDF p.20: 計画・成長戦略に関する記載を確認する。 / 公式PDF p.8: 財務目標・KPIに関する記載を確認する。","status":"corrected","reviewDecisionId":"review-365A-20260721-structured-expansion","detectedAt":"2026-07-21T13:33:00.000Z","correctedAt":"2026-07-21T14:03:00.000Z"},{"id":"correction-5356-20260721-structured-expansion","companyCode":"5356","fieldPath":"category,stage,tier,sourceUrl,document,period,planPublishedDate,lastVerifiedDate,themes,summary,revenue,profit,margin,capital,returnPolicy,highlights,warnings,evidenceRefs,flags,progressAssessment","before":{"stage":"jpx_indexed","pageEvidence":false,"planPublishedDate":null,"revenue":null,"progressAssessment":null},"after":{"stage":"detailed_extracted","pageEvidence":true,"planPublishedDate":"2025-05-15","revenue":"公式PDF p.1で売上高・売上収益に関する数値または方針を確認。対象年度・単位・実績／目標の区分は原文を参照する。","progressAssessment":{"status":"not_comparable","reason":"JPX公式開示資料で計画・数値・方針を確認したが、自動抽出では目標と実績の同一定義・同一単位・同一企業範囲を最終確認できないため、単純な進捗率を作成しない。","sourceRef":"公式PDF p.14: 計画・成長戦略・財務目標・KPI・投資・株主還元に関する記載を確認する。"}},"reason":"美濃窯業の公式計画と進捗評価を比較可能にする。","sourceUrl":"https://www2.jpx.co.jp/disc/53560/140120250514550493.pdf","sourcePage":"公式PDF p.14: 計画・成長戦略・財務目標・KPI・投資・株主還元に関する記載を確認する。 / 公式PDF p.7: 計画・成長戦略・財務目標・KPI・投資・株主還元に関する記載を確認する。 / 公式PDF p.1: 計画・成長戦略・財務目標・KPI・投資・株主還元に関する記載を確認する。","status":"corrected","reviewDecisionId":"review-5356-20260721-structured-expansion","detectedAt":"2026-07-21T13:34:00.000Z","correctedAt":"2026-07-21T14:04:00.000Z"},{"id":"correction-5363-20260721-structured-expansion","companyCode":"5363","fieldPath":"category,stage,tier,sourceUrl,document,period,planPublishedDate,lastVerifiedDate,themes,summary,revenue,profit,margin,capital,returnPolicy,highlights,warnings,evidenceRefs,flags,progressAssessment","before":{"stage":"jpx_indexed","pageEvidence":false,"planPublishedDate":null,"revenue":null,"progressAssessment":null},"after":{"stage":"detailed_extracted","pageEvidence":true,"planPublishedDate":"2023-11-14","revenue":"公式PDF p.1で売上高・売上収益に関する数値または方針を確認。対象年度・単位・実績／目標の区分は原文を参照する。","progressAssessment":{"status":"not_comparable","reason":"JPX公式開示資料で計画・数値・方針を確認したが、自動抽出では目標と実績の同一定義・同一単位・同一企業範囲を最終確認できないため、単純な進捗率を作成しない。","sourceRef":"公式PDF p.1: 計画・成長戦略・財務目標・KPI・投資・株主還元に関する記載を確認する。"}},"reason":"東京窯業の公式計画と進捗評価を比較可能にする。","sourceUrl":"https://www2.jpx.co.jp/disc/53630/140120231113586999.pdf","sourcePage":"公式PDF p.1: 計画・成長戦略・財務目標・KPI・投資・株主還元に関する記載を確認する。 / 公式PDF p.13: 計画・成長戦略・投資・株主還元に関する記載を確認する。 / 公式PDF p.12: 計画・成長戦略・投資・株主還元に関する記載を確認する。","status":"corrected","reviewDecisionId":"review-5363-20260721-structured-expansion","detectedAt":"2026-07-21T13:35:00.000Z","correctedAt":"2026-07-21T14:05:00.000Z"},{"id":"correction-5367-20260721-structured-expansion","companyCode":"5367","fieldPath":"category,stage,tier,sourceUrl,document,period,planPublishedDate,lastVerifiedDate,themes,summary,revenue,profit,margin,capital,returnPolicy,highlights,warnings,evidenceRefs,flags,progressAssessment","before":{"stage":"jpx_indexed","pageEvidence":false,"planPublishedDate":null,"revenue":null,"progressAssessment":null},"after":{"stage":"detailed_extracted","pageEvidence":true,"planPublishedDate":"2025-05-01","revenue":"公式PDF p.5で売上高・売上収益に関する数値または方針を確認。対象年度・単位・実績／目標の区分は原文を参照する。","progressAssessment":{"status":"not_comparable","reason":"JPX公式開示資料で計画・数値・方針を確認したが、自動抽出では目標と実績の同一定義・同一単位・同一企業範囲を最終確認できないため、単純な進捗率を作成しない。","sourceRef":"公式PDF p.12: 計画・成長戦略・財務目標・KPI・投資・株主還元に関する記載を確認する。"}},"reason":"ニッカトーの公式計画と進捗評価を比較可能にする。","sourceUrl":"https://www2.jpx.co.jp/disc/53670/140120250501528612.pdf","sourcePage":"公式PDF p.12: 計画・成長戦略・財務目標・KPI・投資・株主還元に関する記載を確認する。 / 公式PDF p.5: 計画・成長戦略・財務目標・KPIに関する記載を確認する。 / 公式PDF p.10: 計画・成長戦略・財務目標・KPIに関する記載を確認する。","status":"corrected","reviewDecisionId":"review-5367-20260721-structured-expansion","detectedAt":"2026-07-21T13:36:00.000Z","correctedAt":"2026-07-21T14:06:00.000Z"},{"id":"correction-5368-20260721-structured-expansion","companyCode":"5368","fieldPath":"category,stage,tier,sourceUrl,document,period,planPublishedDate,lastVerifiedDate,themes,summary,revenue,profit,margin,capital,returnPolicy,highlights,warnings,evidenceRefs,flags,progressAssessment","before":{"stage":"jpx_indexed","pageEvidence":false,"planPublishedDate":null,"revenue":null,"progressAssessment":null},"after":{"stage":"detailed_extracted","pageEvidence":true,"planPublishedDate":"2026-05-13","revenue":"固定の中期売上高・売上収益は当該公式資料の抽出範囲で確認できない。","progressAssessment":{"status":"not_comparable","reason":"JPX公式開示資料で計画・数値・方針を確認したが、自動抽出では目標と実績の同一定義・同一単位・同一企業範囲を最終確認できないため、単純な進捗率を作成しない。","sourceRef":"公式PDF p.14: 計画・成長戦略に関する記載を確認する。"}},"reason":"日本インシュレーションの公式計画と進捗評価を比較可能にする。","sourceUrl":"https://www2.jpx.co.jp/disc/53680/140120260513530302.pdf","sourcePage":"公式PDF p.14: 計画・成長戦略に関する記載を確認する。 / 公式PDF p.15: 計画・成長戦略に関する記載を確認する。 / 公式PDF p.8: 計画・成長戦略に関する記載を確認する。","status":"corrected","reviewDecisionId":"review-5368-20260721-structured-expansion","detectedAt":"2026-07-21T13:37:00.000Z","correctedAt":"2026-07-21T14:07:00.000Z"},{"id":"correction-5380-20260721-structured-expansion","companyCode":"5380","fieldPath":"category,stage,tier,sourceUrl,document,period,planPublishedDate,lastVerifiedDate,themes,summary,revenue,profit,margin,capital,returnPolicy,highlights,warnings,evidenceRefs,flags,progressAssessment","before":{"stage":"jpx_indexed","pageEvidence":false,"planPublishedDate":null,"revenue":null,"progressAssessment":null},"after":{"stage":"detailed_extracted","pageEvidence":true,"planPublishedDate":"2026-05-08","revenue":"公式PDF p.4で売上高・売上収益に関する数値または方針を確認。対象年度・単位・実績／目標の区分は原文を参照する。","progressAssessment":{"status":"not_comparable","reason":"JPX公式開示資料で計画・数値・方針を確認したが、自動抽出では目標と実績の同一定義・同一単位・同一企業範囲を最終確認できないため、単純な進捗率を作成しない。","sourceRef":"公式PDF p.4: 財務目標・KPI・投資・株主還元に関する記載を確認する。"}},"reason":"新東の公式計画と進捗評価を比較可能にする。","sourceUrl":"https://www2.jpx.co.jp/disc/53800/140120260508518989.pdf","sourcePage":"公式PDF p.4: 財務目標・KPI・投資・株主還元に関する記載を確認する。 / 公式PDF p.1: 財務目標・KPI・投資・株主還元に関する記載を確認する。 / 公式PDF p.8: 財務目標・KPI・投資・株主還元に関する記載を確認する。","status":"corrected","reviewDecisionId":"review-5380-20260721-structured-expansion","detectedAt":"2026-07-21T13:38:00.000Z","correctedAt":"2026-07-21T14:08:00.000Z"},{"id":"correction-5388-20260721-structured-expansion","companyCode":"5388","fieldPath":"category,stage,tier,sourceUrl,document,period,planPublishedDate,lastVerifiedDate,themes,summary,revenue,profit,margin,capital,returnPolicy,highlights,warnings,evidenceRefs,flags,progressAssessment","before":{"stage":"jpx_indexed","pageEvidence":false,"planPublishedDate":null,"revenue":null,"progressAssessment":null},"after":{"stage":"detailed_extracted","pageEvidence":true,"planPublishedDate":"2026-05-15","revenue":"公式PDF p.2で売上高・売上収益に関する数値または方針を確認。対象年度・単位・実績／目標の区分は原文を参照する。","progressAssessment":{"status":"not_comparable","reason":"JPX公式開示資料で計画・数値・方針を確認したが、自動抽出では目標と実績の同一定義・同一単位・同一企業範囲を最終確認できないため、単純な進捗率を作成しない。","sourceRef":"公式PDF p.2: 財務目標・KPI・投資・株主還元に関する記載を確認する。"}},"reason":"クニミネ工業の公式計画と進捗評価を比較可能にする。","sourceUrl":"https://www2.jpx.co.jp/disc/53880/140120260515537761.pdf","sourcePage":"公式PDF p.2: 財務目標・KPI・投資・株主還元に関する記載を確認する。 / 公式PDF p.1: 計画・成長戦略に関する記載を確認する。","status":"corrected","reviewDecisionId":"review-5388-20260721-structured-expansion","detectedAt":"2026-07-21T13:39:00.000Z","correctedAt":"2026-07-21T14:09:00.000Z"},{"id":"correction-5391-20260721-structured-expansion","companyCode":"5391","fieldPath":"category,stage,tier,sourceUrl,document,period,planPublishedDate,lastVerifiedDate,themes,summary,revenue,profit,margin,capital,returnPolicy,highlights,warnings,evidenceRefs,flags,progressAssessment","before":{"stage":"jpx_indexed","pageEvidence":false,"planPublishedDate":null,"revenue":null,"progressAssessment":null},"after":{"stage":"detailed_extracted","pageEvidence":true,"planPublishedDate":"2024-05-08","revenue":"公式PDF p.6で売上高・売上収益に関する数値または方針を確認。対象年度・単位・実績／目標の区分は原文を参照する。","progressAssessment":{"status":"not_comparable","reason":"JPX公式開示資料で計画・数値・方針を確認したが、自動抽出では目標と実績の同一定義・同一単位・同一企業範囲を最終確認できないため、単純な進捗率を作成しない。","sourceRef":"公式PDF p.38: 計画・成長戦略・財務目標・KPIに関する記載を確認する。"}},"reason":"エーアンドエーマテリアルの公式計画と進捗評価を比較可能にする。","sourceUrl":"https://www2.jpx.co.jp/disc/53910/140120240508584511.pdf","sourcePage":"公式PDF p.38: 計画・成長戦略・財務目標・KPIに関する記載を確認する。 / 公式PDF p.6: 計画・成長戦略・財務目標・KPIに関する記載を確認する。 / 公式PDF p.41: 計画・成長戦略・投資・株主還元に関する記載を確認する。","status":"corrected","reviewDecisionId":"review-5391-20260721-structured-expansion","detectedAt":"2026-07-21T13:40:00.000Z","correctedAt":"2026-07-21T14:10:00.000Z"},{"id":"correction-5393-20260721-structured-expansion","companyCode":"5393","fieldPath":"category,stage,tier,sourceUrl,document,period,planPublishedDate,lastVerifiedDate,themes,summary,revenue,profit,margin,capital,returnPolicy,highlights,warnings,evidenceRefs,flags,progressAssessment","before":{"stage":"jpx_indexed","pageEvidence":false,"planPublishedDate":null,"revenue":null,"progressAssessment":null},"after":{"stage":"detailed_extracted","pageEvidence":true,"planPublishedDate":"2022-05-09","revenue":"公式PDF p.1で売上高・売上収益に関する数値または方針を確認。対象年度・単位・実績／目標の区分は原文を参照する。","progressAssessment":{"status":"not_comparable","reason":"JPX公式開示資料で計画・数値・方針を確認したが、自動抽出では目標と実績の同一定義・同一単位・同一企業範囲を最終確認できないため、単純な進捗率を作成しない。","sourceRef":"公式PDF p.1: 計画・成長戦略・財務目標・KPIに関する記載を確認する。"}},"reason":"ニチアスの公式計画と進捗評価を比較可能にする。","sourceUrl":"https://www2.jpx.co.jp/disc/53930/140120220509535319.pdf","sourcePage":"公式PDF p.1: 計画・成長戦略・財務目標・KPIに関する記載を確認する。 / 公式PDF p.2: 計画・成長戦略・投資・株主還元に関する記載を確認する。","status":"corrected","reviewDecisionId":"review-5393-20260721-structured-expansion","detectedAt":"2026-07-21T13:41:00.000Z","correctedAt":"2026-07-21T14:11:00.000Z"}]}
