{
  "version": "quality-score-v2",
  "generatedAt": "2026-07-14T02:14:29.403Z",
  "profileVersion": "2.1",
  "storage": {
    "format": "compact-bitmask",
    "checkKeys": [
      "officialSource",
      "publicationDate",
      "pageEvidence",
      "structuredAnalysis",
      "metricExtraction",
      "progressConnected",
      "humanReviewed",
      "doubleChecked"
    ],
    "checkMaskBits": 8,
    "verboseChecksStoredInBundle": false
  },
  "rule": {
    "weights": {
      "officialSource": 15,
      "publicationDate": 10,
      "pageEvidence": 15,
      "structuredAnalysis": 15,
      "metricExtraction": 15,
      "progressConnected": 10,
      "humanReviewed": 10,
      "doubleChecked": 10
    },
    "extractionStages": [
      "core",
      "detailed_extracted"
    ],
    "fiveStars": "all eight evidence and review checks must be true",
    "fourStars": "score >= 65",
    "threeStars": "score >= 45",
    "twoStars": "official source confirmed",
    "oneStar": "coverage only or insufficient evidence"
  },
  "before": {
    "1": 902,
    "2": 92,
    "3": 0,
    "4": 196,
    "5": 10
  },
  "after": {
    "1": 902,
    "2": 92,
    "3": 0,
    "4": 196,
    "5": 10
  },
  "byStage": {
    "core": {
      "companies": 30,
      "distribution": {
        "1": 0,
        "2": 0,
        "3": 0,
        "4": 20,
        "5": 10
      },
      "averageScore": 89.7
    },
    "detailed_extracted": {
      "companies": 176,
      "distribution": {
        "1": 0,
        "2": 0,
        "3": 0,
        "4": 176,
        "5": 0
      },
      "averageScore": 73.9
    },
    "source_indexed": {
      "companies": 92,
      "distribution": {
        "1": 0,
        "2": 92,
        "3": 0,
        "4": 0,
        "5": 0
      },
      "averageScore": 15.7
    },
    "jpx_indexed": {
      "companies": 902,
      "distribution": {
        "1": 902,
        "2": 0,
        "3": 0,
        "4": 0,
        "5": 0
      },
      "averageScore": null
    }
  },
  "bundle": {
    "sha256": "1787931c2c2af1313d4e47438ec76b2f05f00100189740e6b64baf4af1a0b008",
    "compressedBytes": 185455,
    "parts": 43
  }
}
