{
  "version": "quality-score-v2",
  "generatedAt": "2026-07-21T01:14:08.799Z",
  "profileVersion": "2.4",
  "storage": {
    "format": "compact-bitmask",
    "checkKeys": [
      "officialSource",
      "publicationDate",
      "pageEvidence",
      "structuredAnalysis",
      "metricExtraction",
      "progressConnected",
      "humanReviewed",
      "doubleChecked"
    ],
    "checkMaskBits": 8,
    "verboseChecksStoredInBundle": false
  },
  "rule": {
    "weights": {
      "officialSource": 15,
      "publicationDate": 10,
      "pageEvidence": 15,
      "structuredAnalysis": 15,
      "metricExtraction": 15,
      "progressConnected": 10,
      "humanReviewed": 10,
      "doubleChecked": 10
    },
    "extractionStages": [
      "core",
      "detailed_extracted"
    ],
    "fiveStars": "all eight evidence and review checks must be true",
    "fourStars": "score >= 65",
    "threeStars": "score >= 45",
    "twoStars": "official source confirmed",
    "oneStar": "coverage only or insufficient evidence"
  },
  "before": {
    "1": 216,
    "2": 0,
    "3": 1,
    "4": 18,
    "5": 965
  },
  "after": {
    "1": 216,
    "2": 0,
    "3": 1,
    "4": 18,
    "5": 965
  },
  "byStage": {
    "core": {
      "companies": 979,
      "distribution": {
        "1": 0,
        "2": 0,
        "3": 1,
        "4": 13,
        "5": 965
      },
      "averageScore": 99.5
    },
    "detailed_extracted": {
      "companies": 5,
      "distribution": {
        "1": 0,
        "2": 0,
        "3": 0,
        "4": 5,
        "5": 0
      },
      "averageScore": 68
    },
    "source_indexed": {
      "companies": 0,
      "distribution": {
        "1": 0,
        "2": 0,
        "3": 0,
        "4": 0,
        "5": 0
      },
      "averageScore": null
    },
    "jpx_indexed": {
      "companies": 216,
      "distribution": {
        "1": 216,
        "2": 0,
        "3": 0,
        "4": 0,
        "5": 0
      },
      "averageScore": null
    }
  },
  "bundle": {
    "sha256": "1b5adf4dbf5b23528114b733f88f618b92767f010f9f465e7eb279a879a23bbc",
    "compressedBytes": 385854,
    "parts": 43
  }
}
